Workbook

Sheet Tally_Bank_Ledger
A1: Tally Prime - HDFC Bank A/c Ledger (Books) - April 2026
A2: Both entries are from the Nexus Tech Tally data. Debit = money in, Credit = money out.
A4: Sr | B4: Date | C4: Vch Type | D4: Vch No | E4: Particulars | F4: Chq / Ref No | G4: Debit (Receipt) | H4: Credit (Payment) | I4: Net | J4: Running Balance | K4: Match Key (Ref|Net) | L4: Source
A5: 1 | B5: 46113 | C5: Receipt | D5: 1 | E5: Share Capital A/c | F5: NEFT-CAP-001 | G5: 1000000 | I5: =IF(AND(G5="",H5=""),"",N(G5)-N(H5)) -> 1000000 | J5: =IF(I5="","",SUM(I$5:I5)) -> 1000000 | K5: =IF(I5="","",F5&"|"&I5) -> NEFT-CAP-001|1000000 | L5: Tally (Receipt Vch 1)
A6: 2 | B6: 46113 | C6: Payment | D6: 1 | E6: Apex Office Realty (Rent 45,000 + TDS 5,000) | F6: CHQ100001 | H6: 50000 | I6: =IF(AND(G6="",H6=""),"",N(G6)-N(H6)) -> -50000 | J6: =IF(I6="","",SUM(I$5:I6)) -> 950000 | K6: =IF(I6="","",F6&"|"&I6) -> CHQ100001|-50000 | L6: Tally (Payment Vch 1)
A7: 3 | I7: =IF(AND(G7="",H7=""),"",N(G7)-N(H7)) | J7: =IF(I7="","",SUM(I$5:I7)) | K7: =IF(I7="","",F7&"|"&I7)
A8: 4 | I8: =IF(AND(G8="",H8=""),"",N(G8)-N(H8)) | J8: =IF(I8="","",SUM(I$5:I8)) | K8: =IF(I8="","",F8&"|"&I8)
A9: 5 | I9: =IF(AND(G9="",H9=""),"",N(G9)-N(H9)) | J9: =IF(I9="","",SUM(I$5:I9)) | K9: =IF(I9="","",F9&"|"&I9)
E10: TOTAL / CLOSING BALANCE | G10: =SUM(G5:G9) -> 1000000 | H10: =SUM(H5:H9) -> 50000 | J10: =G10-H10 -> 950000
A12: Legend: blue = input cells. Assumption: Payment Vch 1 is a single bank payment of Rs 50,000 (Apex rent 45,000 + TDS 5,000 deposited), as implied by the Tally Trial Balance (bank = 9,50,000).
A13: Chq / Ref No values are placeholders - replace with actual cheque numbers from Tally. Rows 5-9 hold up to 5 entries.

Sheet Bank_Statement
A1: HDFC Bank Statement (dummy) - April 2026
A2: Practice statement prepared to match the Tally entries. The rent cheque CHQ100001 is assumed not yet presented at month-end. Replace with the real statement when using actual data.
A4: Sr | B4: Date | C4: Description | D4: Chq / Ref No | E4: Withdrawal | F4: Deposit | G4: Net | H4: Balance | I4: Match Key (Ref|Net)
A5: 1 | B5: 46113 | C5: NEFT credit - share capital | D5: NEFT-CAP-001 | F5: 1000000 | G5: =IF(AND(E5="",F5=""),"",N(F5)-N(E5)) -> 1000000 | H5: =IF(G5="","",SUM(G$5:G5)) -> 1000000 | I5: =IF(G5="","",D5&"|"&G5) -> NEFT-CAP-001|1000000
A6: 2 | G6: =IF(AND(E6="",F6=""),"",N(F6)-N(E6)) | H6: =IF(G6="","",SUM(G$5:G6)) | I6: =IF(G6="","",D6&"|"&G6)
A7: 3 | G7: =IF(AND(E7="",F7=""),"",N(F7)-N(E7)) | H7: =IF(G7="","",SUM(G$5:G7)) | I7: =IF(G7="","",D7&"|"&G7)
A8: 4 | G8: =IF(AND(E8="",F8=""),"",N(F8)-N(E8)) | H8: =IF(G8="","",SUM(G$5:G8)) | I8: =IF(G8="","",D8&"|"&G8)
A9: 5 | G9: =IF(AND(E9="",F9=""),"",N(F9)-N(E9)) | H9: =IF(G9="","",SUM(G$5:G9)) | I9: =IF(G9="","",D9&"|"&G9)
C10: TOTAL / CLOSING BALANCE | E10: =SUM(E5:E9) -> 0 | F10: =SUM(F5:F9) -> 1000000 | H10: =F10-E10 -> 1000000
A12: Assumption: opening bank balance is nil (company starts on 1-Apr-26). Blue = input cells.

Sheet BRS_Matching
A1: Bank Reconciliation - Entry Matching
A2: Match is on Chq/Ref No + amount (INDEX/MATCH on helper key). Section A: Tally entries vs bank. Section B: bank entries vs Tally.
A4: SECTION A: Entries in Tally Bank Ledger
A5: Sr | B5: Date | C5: Particulars | D5: Chq / Ref No | E5: Tally Amount (+in / -out) | F5: In Bank? | G5: Bank Date | H5: Status | I5: Deposit in Transit | J5: Uncleared Cheque
A6: =IF(Tally_Bank_Ledger!I5="","",ROW()-5) -> 1 | B6: =IF($A6="","",Tally_Bank_Ledger!B5) -> 46113 | C6: =IF($A6="","",Tally_Bank_Ledger!E5) -> Share Capital A/c | D6: =IF($A6="","",Tally_Bank_Ledger!F5) -> NEFT-CAP-001 | E6: =IF($A6="","",Tally_Bank_Ledger!I5) -> 1000000 | F6: =IF($A6="","",IF(ISNUMBER(MATCH(Tally_Bank_Ledger!K5,Bank_Statement!$I$5:$I$9,0)),"Yes","No")) -> Yes | G6: =IF($A6="","",IF(F6="Yes",INDEX(Bank_Statement!$B$5:$B$9,MATCH(Tally_Bank_Ledger!K5,Bank_Statement!$I$5:$I$9,0)),"-")) -> 46113 | H6: =IF($A6="","",IF(F6="Yes","Matched",IF(E6>0,"Deposit in Transit","Uncleared Cheque"))) -> Matched | I6: =IF($A6="","",IF(H6="Deposit in Transit",E6,0)) -> 0 | J6: =IF($A6="","",IF(H6="Uncleared Cheque",-E6,0)) -> 0
A7: =IF(Tally_Bank_Ledger!I6="","",ROW()-5) -> 2 | B7: =IF($A7="","",Tally_Bank_Ledger!B6) -> 46113 | C7: =IF($A7="","",Tally_Bank_Ledger!E6) -> Apex Office Realty (Rent 45,000 + TDS 5,000) | D7: =IF($A7="","",Tally_Bank_Ledger!F6) -> CHQ100001 | E7: =IF($A7="","",Tally_Bank_Ledger!I6) -> -50000 | F7: =IF($A7="","",IF(ISNUMBER(MATCH(Tally_Bank_Ledger!K6,Bank_Statement!$I$5:$I$9,0)),"Yes","No")) -> No | G7: =IF($A7="","",IF(F7="Yes",INDEX(Bank_Statement!$B$5:$B$9,MATCH(Tally_Bank_Ledger!K6,Bank_Statement!$I$5:$I$9,0)),"-")) -> - | H7: =IF($A7="","",IF(F7="Yes","Matched",IF(E7>0,"Deposit in Transit","Uncleared Cheque"))) -> Uncleared Cheque | I7: =IF($A7="","",IF(H7="Deposit in Transit",E7,0)) -> 0 | J7: =IF($A7="","",IF(H7="Uncleared Cheque",-E7,0)) -> 50000
A8: =IF(Tally_Bank_Ledger!I7="","",ROW()-5) | B8: =IF($A8="","",Tally_Bank_Ledger!B7) | C8: =IF($A8="","",Tally_Bank_Ledger!E7) | D8: =IF($A8="","",Tally_Bank_Ledger!F7) | E8: =IF($A8="","",Tally_Bank_Ledger!I7) | F8: =IF($A8="","",IF(ISNUMBER(MATCH(Tally_Bank_Ledger!K7,Bank_Statement!$I$5:$I$9,0)),"Yes","No")) | G8: =IF($A8="","",IF(F8="Yes",INDEX(Bank_Statement!$B$5:$B$9,MATCH(Tally_Bank_Ledger!K7,Bank_Statement!$I$5:$I$9,0)),"-")) | H8: =IF($A8="","",IF(F8="Yes","Matched",IF(E8>0,"Deposit in Transit","Uncleared Cheque"))) | I8: =IF($A8="","",IF(H8="Deposit in Transit",E8,0)) | J8: =IF($A8="","",IF(H8="Uncleared Cheque",-E8,0))
A9: =IF(Tally_Bank_Ledger!I8="","",ROW()-5) | B9: =IF($A9="","",Tally_Bank_Ledger!B8) | C9: =IF($A9="","",Tally_Bank_Ledger!E8) | D9: =IF($A9="","",Tally_Bank_Ledger!F8) | E9: =IF($A9="","",Tally_Bank_Ledger!I8) | F9: =IF($A9="","",IF(ISNUMBER(MATCH(Tally_Bank_Ledger!K8,Bank_Statement!$I$5:$I$9,0)),"Yes","No")) | G9: =IF($A9="","",IF(F9="Yes",INDEX(Bank_Statement!$B$5:$B$9,MATCH(Tally_Bank_Ledger!K8,Bank_Statement!$I$5:$I$9,0)),"-")) | H9: =IF($A9="","",IF(F9="Yes","Matched",IF(E9>0,"Deposit in Transit","Uncleared Cheque"))) | I9: =IF($A9="","",IF(H9="Deposit in Transit",E9,0)) | J9: =IF($A9="","",IF(H9="Uncleared Cheque",-E9,0))
A10: =IF(Tally_Bank_Ledger!I9="","",ROW()-5) | B10: =IF($A10="","",Tally_Bank_Ledger!B9) | C10: =IF($A10="","",Tally_Bank_Ledger!E9) | D10: =IF($A10="","",Tally_Bank_Ledger!F9) | E10: =IF($A10="","",Tally_Bank_Ledger!I9) | F10: =IF($A10="","",IF(ISNUMBER(MATCH(Tally_Bank_Ledger!K9,Bank_Statement!$I$5:$I$9,0)),"Yes","No")) | G10: =IF($A10="","",IF(F10="Yes",INDEX(Bank_Statement!$B$5:$B$9,MATCH(Tally_Bank_Ledger!K9,Bank_Statement!$I$5:$I$9,0)),"-")) | H10: =IF($A10="","",IF(F10="Yes","Matched",IF(E10>0,"Deposit in Transit","Uncleared Cheque"))) | I10: =IF($A10="","",IF(H10="Deposit in Transit",E10,0)) | J10: =IF($A10="","",IF(H10="Uncleared Cheque",-E10,0))
C11: TOTAL | I11: =SUM(I6:I10) -> 0 | J11: =SUM(J6:J10) -> 50000
A13: SECTION B: Entries in Bank Statement
A14: Sr | B14: Date | C14: Description | D14: Chq / Ref No | E14: Bank Amount (+in / -out) | F14: In Tally? | H14: Status | I14: Direct Credit not in Books | J14: Bank Charges / Debit not in Books
A15: =IF(Bank_Statement!G5="","",ROW()-14) -> 1 | B15: =IF($A15="","",Bank_Statement!B5) -> 46113 | C15: =IF($A15="","",Bank_Statement!C5) -> NEFT credit - share capital | D15: =IF($A15="","",Bank_Statement!D5) -> NEFT-CAP-001 | E15: =IF($A15="","",Bank_Statement!G5) -> 1000000 | F15: =IF($A15="","",IF(ISNUMBER(MATCH(Bank_Statement!I5,Tally_Bank_Ledger!$K$5:$K$9,0)),"Yes","No")) -> Yes | H15: =IF($A15="","",IF(F15="Yes","Matched",IF(E15>0,"Direct Credit - Not in Books","Bank Charges / Debit - Not in Books"))) -> Matched | I15: =IF($A15="","",IF(H15="Direct Credit - Not in Books",E15,0)) -> 0 | J15: =IF($A15="","",IF(H15="Bank Charges / Debit - Not in Books",-E15,0)) -> 0
A16: =IF(Bank_Statement!G6="","",ROW()-14) | B16: =IF($A16="","",Bank_Statement!B6) | C16: =IF($A16="","",Bank_Statement!C6) | D16: =IF($A16="","",Bank_Statement!D6) | E16: =IF($A16="","",Bank_Statement!G6) | F16: =IF($A16="","",IF(ISNUMBER(MATCH(Bank_Statement!I6,Tally_Bank_Ledger!$K$5:$K$9,0)),"Yes","No")) | H16: =IF($A16="","",IF(F16="Yes","Matched",IF(E16>0,"Direct Credit - Not in Books","Bank Charges / Debit - Not in Books"))) | I16: =IF($A16="","",IF(H16="Direct Credit - Not in Books",E16,0)) | J16: =IF($A16="","",IF(H16="Bank Charges / Debit - Not in Books",-E16,0))
A17: =IF(Bank_Statement!G7="","",ROW()-14) | B17: =IF($A17="","",Bank_Statement!B7) | C17: =IF($A17="","",Bank_Statement!C7) | D17: =IF($A17="","",Bank_Statement!D7) | E17: =IF($A17="","",Bank_Statement!G7) | F17: =IF($A17="","",IF(ISNUMBER(MATCH(Bank_Statement!I7,Tally_Bank_Ledger!$K$5:$K$9,0)),"Yes","No")) | H17: =IF($A17="","",IF(F17="Yes","Matched",IF(E17>0,"Direct Credit - Not in Books","Bank Charges / Debit - Not in Books"))) | I17: =IF($A17="","",IF(H17="Direct Credit - Not in Books",E17,0)) | J17: =IF($A17="","",IF(H17="Bank Charges / Debit - Not in Books",-E17,0))
A18: =IF(Bank_Statement!G8="","",ROW()-14) | B18: =IF($A18="","",Bank_Statement!B8) | C18: =IF($A18="","",Bank_Statement!C8) | D18: =IF($A18="","",Bank_Statement!D8) | E18: =IF($A18="","",Bank_Statement!G8) | F18: =IF($A18="","",IF(ISNUMBER(MATCH(Bank_Statement!I8,Tally_Bank_Ledger!$K$5:$K$9,0)),"Yes","No")) | H18: =IF($A18="","",IF(F18="Yes","Matched",IF(E18>0,"Direct Credit - Not in Books","Bank Charges / Debit - Not in Books"))) | I18: =IF($A18="","",IF(H18="Direct Credit - Not in Books",E18,0)) | J18: =IF($A18="","",IF(H18="Bank Charges / Debit - Not in Books",-E18,0))
A19: =IF(Bank_Statement!G9="","",ROW()-14) | B19: =IF($A19="","",Bank_Statement!B9) | C19: =IF($A19="","",Bank_Statement!C9) | D19: =IF($A19="","",Bank_Statement!D9) | E19: =IF($A19="","",Bank_Statement!G9) | F19: =IF($A19="","",IF(ISNUMBER(MATCH(Bank_Statement!I9,Tally_Bank_Ledger!$K$5:$K$9,0)),"Yes","No")) | H19: =IF($A19="","",IF(F19="Yes","Matched",IF(E19>0,"Direct Credit - Not in Books","Bank Charges / Debit - Not in Books"))) | I19: =IF($A19="","",IF(H19="Direct Credit - Not in Books",E19,0)) | J19: =IF($A19="","",IF(H19="Bank Charges / Debit - Not in Books",-E19,0))
C20: TOTAL | I20: =SUM(I15:I19) -> 0 | J20: =SUM(J15:J19) -> 0

Sheet BRS_Statement
A1: Bank Reconciliation Statement - HDFC Bank A/c
A2: Nexus Tech Distribution Pvt. Ltd. | As on 30-Apr-2026 | Rs
A4: Particulars | B4: Amount (Rs)
A5: Balance as per Tally (Books) | B5: =Tally_Bank_Ledger!J10 -> 950000
A6: Less: Deposits in transit (recorded in Tally, not yet credited by bank) | B6: =-BRS_Matching!I11 -> 0
A7: Add: Cheques issued but not presented (recorded in Tally, not yet debited by bank) | B7: =BRS_Matching!J11 -> 50000
A8: Add: Direct credits in bank not yet recorded in Tally | B8: =BRS_Matching!I20 -> 0
A9: Less: Bank charges / direct debits in bank not yet recorded in Tally | B9: =-BRS_Matching!J20 -> 0
A10: Balance as per Bank Statement (computed) | B10: =SUM(B5:B9) -> 1000000
A11: Balance as per Bank Statement (actual) | B11: =Bank_Statement!H10 -> 1000000
A12: Difference (must be 0) | B12: =B10-B11 -> 0
A13: Status | B13: =IF(ABS(B12)<0.5,"RECONCILED","NOT RECONCILED") -> RECONCILED
A15: Entries to pass in Tally (items in bank but not in books)
A16: Entry | B16: Amount (Rs)
A17: Receipt: Dr HDFC Bank A/c (direct credit from customer, NEFT) | B17: =BRS_Matching!I20 -> 0
A18: Payment: Cr HDFC Bank A/c (bank service charges) | B18: =BRS_Matching!J20 -> 0
A20: No entry is needed in Tally: every bank item is already recorded. The uncleared cheque needs no entry; set its bank date in Tally (Banking > Bank Reconciliation) once the bank clears it.

Sheet AR_AP_Data
A1: Open Invoices - Receivables and Payables
A2: All invoices are from the Nexus Tech Tally data (invoice nos. are placeholders). Days = As-on date minus Invoice date.
A4: Sr | B4: Type | C4: Party | D4: Invoice No | E4: Invoice Date | F4: Outstanding Amount (Rs) | G4: Days Outstanding | H4: Bucket | I4: Source
A5: 1 | B5: Receivable | C5: Infotech Solutions Ltd | D5: SI/26-27/001 | E5: 46113 | F5: 354000 | G5: =IF(E5="","",Ageing_Summary!$C$3-E5) -> 29 | H5: =IF(G5="","",IF(G5<=30,"0-30 days",IF(G5<=60,"31-60 days","60+ days"))) -> 0-30 days | I5: Tally (Sales Vch 1)
A6: 2 | B6: Payable | C6: Delta Systems Pvt Ltd | D6: DS/26-27/001 | E6: 46113 | F6: 118000 | G6: =IF(E6="","",Ageing_Summary!$C$3-E6) -> 29 | H6: =IF(G6="","",IF(G6<=30,"0-30 days",IF(G6<=60,"31-60 days","60+ days"))) -> 0-30 days | I6: Tally (Purch Vch 1)
A7: 3 | B7: Payable | C7: Global Tech Traders | D7: GTT/26-27/001 | E7: 46113 | F7: 236000 | G7: =IF(E7="","",Ageing_Summary!$C$3-E7) -> 29 | H7: =IF(G7="","",IF(G7<=30,"0-30 days",IF(G7<=60,"31-60 days","60+ days"))) -> 0-30 days | I7: Tally (Purch Vch 2)
A8: 4 | G8: =IF(E8="","",Ageing_Summary!$C$3-E8) | H8: =IF(G8="","",IF(G8<=30,"0-30 days",IF(G8<=60,"31-60 days","60+ days")))
A9: 5 | G9: =IF(E9="","",Ageing_Summary!$C$3-E9) | H9: =IF(G9="","",IF(G9<=30,"0-30 days",IF(G9<=60,"31-60 days","60+ days")))
A10: 6 | G10: =IF(E10="","",Ageing_Summary!$C$3-E10) | H10: =IF(G10="","",IF(G10<=30,"0-30 days",IF(G10<=60,"31-60 days","60+ days")))
A12: Legend: blue = input cells. Type must be exactly "Receivable" or "Payable". Rows 5-10 hold up to 6 invoices. Change the As-on date on Ageing_Summary!C3.

Sheet Ageing_Summary
A1: Ageing Analysis - Receivables and Payables
A2: Built with SUMIFS on AR_AP_Data (gives the same result as a PivotTable; steps to build a real PivotTable are on the Pivot_Steps sheet).
A3: As-on date | C3: 46142 | D3: Change this date to re-age all invoices (assumption: month-end 30-Apr-26).
A5: A. ACCOUNTS RECEIVABLE AGEING (amount due from customers)
A6: Party | B6: 0-30 days | C6: 31-60 days | D6: 60+ days | E6: Total | F6: % of Total
A7: Infotech Solutions Ltd | B7: =SUMIFS(AR_AP_Data!$F$5:$F$10,AR_AP_Data!$B$5:$B$10,"Receivable",AR_AP_Data!$C$5:$C$10,$A7,AR_AP_Data!$H$5:$H$10,B$6) -> 354000 | C7: =SUMIFS(AR_AP_Data!$F$5:$F$10,AR_AP_Data!$B$5:$B$10,"Receivable",AR_AP_Data!$C$5:$C$10,$A7,AR_AP_Data!$H$5:$H$10,C$6) -> 0 | D7: =SUMIFS(AR_AP_Data!$F$5:$F$10,AR_AP_Data!$B$5:$B$10,"Receivable",AR_AP_Data!$C$5:$C$10,$A7,AR_AP_Data!$H$5:$H$10,D$6) -> 0 | E7: =SUM(B7:D7) -> 354000 | F7: =IF($E$8=0,0,E7/$E$8) -> 1
A8: TOTAL | B8: =SUM(B7:B7) -> 354000 | C8: =SUM(C7:C7) -> 0 | D8: =SUM(D7:D7) -> 0 | E8: =SUM(E7:E7) -> 354000 | F8: =IF($E$8=0,0,E8/$E$8) -> 1
A9: % of Total | B9: =IF($E$8=0,0,B8/$E$8) -> 1 | C9: =IF($E$8=0,0,C8/$E$8) -> 0 | D9: =IF($E$8=0,0,D8/$E$8) -> 0 | E9: =IF($E$8=0,0,E8/$E$8) -> 1
A12: B. ACCOUNTS PAYABLE AGEING (amount due to vendors)
A13: Party | B13: 0-30 days | C13: 31-60 days | D13: 60+ days | E13: Total | F13: % of Total
A14: Delta Systems Pvt Ltd | B14: =SUMIFS(AR_AP_Data!$F$5:$F$10,AR_AP_Data!$B$5:$B$10,"Payable",AR_AP_Data!$C$5:$C$10,$A14,AR_AP_Data!$H$5:$H$10,B$13) -> 118000 | C14: =SUMIFS(AR_AP_Data!$F$5:$F$10,AR_AP_Data!$B$5:$B$10,"Payable",AR_AP_Data!$C$5:$C$10,$A14,AR_AP_Data!$H$5:$H$10,C$13) -> 0 | D14: =SUMIFS(AR_AP_Data!$F$5:$F$10,AR_AP_Data!$B$5:$B$10,"Payable",AR_AP_Data!$C$5:$C$10,$A14,AR_AP_Data!$H$5:$H$10,D$13) -> 0 | E14: =SUM(B14:D14) -> 118000 | F14: =IF($E$16=0,0,E14/$E$16) -> 0.33333333
A15: Global Tech Traders | B15: =SUMIFS(AR_AP_Data!$F$5:$F$10,AR_AP_Data!$B$5:$B$10,"Payable",AR_AP_Data!$C$5:$C$10,$A15,AR_AP_Data!$H$5:$H$10,B$13) -> 236000 | C15: =SUMIFS(AR_AP_Data!$F$5:$F$10,AR_AP_Data!$B$5:$B$10,"Payable",AR_AP_Data!$C$5:$C$10,$A15,AR_AP_Data!$H$5:$H$10,C$13) -> 0 | D15: =SUMIFS(AR_AP_Data!$F$5:$F$10,AR_AP_Data!$B$5:$B$10,"Payable",AR_AP_Data!$C$5:$C$10,$A15,AR_AP_Data!$H$5:$H$10,D$13) -> 0 | E15: =SUM(B15:D15) -> 236000 | F15: =IF($E$16=0,0,E15/$E$16) -> 0.66666667
A16: TOTAL | B16: =SUM(B14:B15) -> 354000 | C16: =SUM(C14:C15) -> 0 | D16: =SUM(D14:D15) -> 0 | E16: =SUM(E14:E15) -> 354000 | F16: =IF($E$16=0,0,E16/$E$16) -> 1
A17: % of Total | B17: =IF($E$16=0,0,B16/$E$16) -> 1 | C17: =IF($E$16=0,0,C16/$E$16) -> 0 | D17: =IF($E$16=0,0,D16/$E$16) -> 0 | E17: =IF($E$16=0,0,E16/$E$16) -> 1
A20: C. NET RECEIVABLES / PAYABLES POSITION
A21: Particulars | B21: 0-30 days | C21: 31-60 days | D21: 60+ days | E21: Total
A22: Receivables | B22: =B8 -> 354000 | C22: =C8 -> 0 | D22: =D8 -> 0 | E22: =E8 -> 354000
A23: Payables | B23: =B16 -> 354000 | C23: =C16 -> 0 | D23: =D16 -> 0 | E23: =E16 -> 354000
A24: Net (Receivables - Payables) | B24: =B22-B23 -> 0 | C24: =C22-C23 -> 0 | D24: =D22-D23 -> 0 | E24: =E22-E23 -> 0
A26: Checks
A27: Receivable total - AR_AP_Data total (must be 0) | B27: =E8-SUMIFS(AR_AP_Data!$F$5:$F$10,AR_AP_Data!$B$5:$B$10,"Receivable") -> 0
A28: Payable total - AR_AP_Data total (must be 0) | B28: =E16-SUMIFS(AR_AP_Data!$F$5:$F$10,AR_AP_Data!$B$5:$B$10,"Payable") -> 0
A29: Note: if you add a new party in AR_AP_Data, add its name in column A of the table above, otherwise the check cell will show a difference.

Sheet Pivot_Steps
A1: How to create the real PivotTable (Excel)
A2: Do this on the AR_AP_Data sheet after the SUMIFS ageing is working. It should give the same totals.
A4: Step | B4: What to do
A5: 1 | B5: Click any cell inside the table on AR_AP_Data (for example C5).
A6: 2 | B6: Go to Insert > PivotTable > From Table/Range > choose a New Worksheet > OK.
A7: 3 | B7: Drag Type to Filters, Party to Rows, Bucket to Columns, and Outstanding Amount (Rs) to Values (Sum).
A8: 4 | B8: Use the Type filter: select Receivable for AR ageing, then Payable for AP ageing. Compare totals with Ageing_Summary.
A9: 5 | B9: Optional: Insert > PivotChart > Clustered Column to show the ageing buckets as a chart.
A10: 6 | B10: If blank rows appear in the PivotTable, untick (blank) in the Rows or Columns filter.
A11: 7 | B11: After editing data, right-click the PivotTable > Refresh.
