Workbook

Sheet README
A1: Financial Statement Analysis Dashboard — TCS
A2: Excel + Power BI Portfolio Project
A4: HOW TO USE THIS WORKBOOK
A5: 1. Get data from screener.in (search 'TCS' -> Balance Sheet / Profit & Loss / Cash Flow tabs) or tcs.com > Investors > Annual Reports.
A6: 2. Fill in ONLY the yellow cells on the 'Raw Data - PL', 'Raw Data - BS', 'Raw Data - CF' sheets with actual figures in Rs. Crore for FY21-FY25.
A7: 3. 'Ratio Analysis' and 'Trend Analysis' sheets are 100% FORMULAS linked to the Raw Data sheets — they update automatically once you fill in the inputs.
A8: 4. Once populated, run File > Import in Power BI Desktop (Get Data > Excel Workbook) and build visuals on top of the Ratio Analysis and Trend Analysis tables.
A9: 5. Write your own analyst-style commentary on the 'Insights' sheet — this is what turns it from a spreadsheet into a portfolio piece.
A11: SHEET GUIDE
A12: Raw Data - PL : Revenue, expenses, profit figures (fill yellow cells)
A13: Raw Data - BS : Assets, liabilities, equity figures (fill yellow cells)
A14: Raw Data - CF : Operating / investing / financing cash flow (fill yellow cells)
... A23: Green text = formula linking to another sheet

Sheet Raw Data - PL
A1: Profit & Loss Statement (Rs. Crore)
A3: Particulars | B3: FY21 | C3: FY22 | D3: FY23 | E3: FY24 | F3: FY25
A4: Revenue from Operations | B4: 164177 | C4: 191754 | D4: 225458 | E4: 240893 | F4: 255324
A5: Other Income | B5: 2497 | C5: 3234 | D5: 2670 | E5: 3727 | F5: 3166
A6: Total Income | B6: 166674 | C6: 194988 | D6: 228128 | E6: 244620 | F6: 258490
A7: Employee Benefit Expense | B7: 91814 | C7: 107554 | D7: 127522 | E7: 140132 | F7: 145788
A8: Other Expenses | B8: 29882 | C8: 35747 | D8: 43699 | E8: 41450 | F8: 47371
A9: Total Operating Expenses | B9: 121696 | C9: 143301 | D9: 171221 | E9: 181582 | F9: 193159
A10: EBITDA | B10: 46546 | C10: 53057 | D10: 59260 | E10: 64295 | F10: 67407
A11: Depreciation & Amortisation | B11: 4065 | C11: 4604 | D11: 5023 | E11: 4984 | F11: 5242
A12: EBIT (Operating Profit) | B12: 42481 | C12: 48453 | D12: 54237 | E12: 59311 | F12: 62165
A13: Finance Costs (Interest) | B13: 0 | C13: 0 | D13: 0 | E13: 0 | F13: 0
A14: Profit Before Tax (PBT) | B14: 44978 | C14: 51687 | D14: 56907 | E14: 63038 | F14: 65331
A15: Tax Expense | B15: 11458 | C15: 13238 | D15: 14604 | E15: 16262 | F15: 16534
A16: Profit After Tax (PAT) | B16: 33388 | C16: 38327 | D16: 42147 | E16: 46585 | F16: 48553
A19: Source: TCS Investor Relations Data Sheet (Consolidated, IFRS), tcs.com/investor-relations

Sheet Raw Data - BS
A1: Balance Sheet (Rs. Crore)
A3: Particulars | B3: FY21 | C3: FY22 | D3: FY23 | E3: FY24 | F3: FY25
A4: Share Capital | B4: 370 | C4: 366 | D4: 366 | E4: 362 | F4: 362
A5: Reserves & Surplus | B5: 88185 | C5: 90893 | D5: 92176 | E5: 92250 | F5: 96520
A6: Total Shareholders' Equity (incl. NCI) | B6: 89230 | C6: 91966 | D6: 93324 | E6: 93442 | F6: 97897
A7: Long-Term Borrowings | B7: 6503 | C7: 6368 | D7: 6203 | E7: 6516 | F7: 7838
A8: Short-Term Borrowings | B8: 0 | C8: 0 | D8: 0 | E8: 0 | F8: 0
A9: Trade Payables | B9: 7860 | C9: 8045 | D9: 10515 | E9: 9981 | F9: 13909
A10: Other Current Liabilities | B10: 26295 | C10: 34306 | D10: 33043 | E10: 36123 | F10: 39092
A11: Total Current Liabilities | B11: 34155 | C11: 42351 | D11: 43558 | E11: 46104 | F11: 53001
A12: Total Debt | B12: 6503 | C12: 6368 | D12: 6203 | E12: 6516 | F12: 7838
A13: Other Long-Term Liabilities | B13: 2993 | C13: 2949 | D13: 2684 | E13: 2510 | F13: 3019
A14: Total Liabilities | B14: 43651 | C14: 51668 | D14: 52445 | E14: 55130 | F14: 63858
A15: Net Fixed Assets | B15: 24196 | C15: 24752 | D15: 24028 | E15: 23609 | F15: 27171
... A21: Total Assets | B21: 132881 | C21: 143634 | D21: 145769 | E21: 148572 | F21: 161755
A24: Source: TCS Investor Relations Data Sheet (Consolidated, IFRS) and Consolidated Statement of Changes in Equity, tcs.com/investor-relations
A26: Note: Total Shareholders' Equity (row 6) has been corrected to include Non-Controlling Interests (675 / 707 / 782 / 830 / 1,015 Cr for FY21-FY25) — TCS's consolidated subsidiaries' minority stake, sourced from TCS's audited Statement of Changes in Equity. This was missing in the original data, which caused Total Assets to not equal Total Equity + Total Liabilities.

Sheet Raw Data - CF
A1: Cash Flow Statement (Rs. Crore)
A3: Particulars | B3: FY21 | C3: FY22 | D3: FY23 | E3: FY24 | F3: FY25
A4: Cash Flow from Operating Activities
A5: Cash Flow from Investing Activities
A6: Cash Flow from Financing Activities
A7: Net Increase / Decrease in Cash
A9: NOTE: Cash Flow Statement was not available in the TCS Investor Relations Data Sheet used for the P&L and Balance Sheet above. Source separately from the Annual Report (Consolidated Cash Flow Statement) if required, or omit Cash Flow ratios from the project scope.

Sheet Ratio Analysis
A1: Ratio Analysis
A3: Ratio | B3: FY21 | C3: FY22 | D3: FY23 | E3: FY24 | F3: FY25
A4: LIQUIDITY RATIOS
A5: Current Ratio | B5: =IFERROR('Raw Data - BS'!B20/'Raw Data - BS'!B11,0) -> 2.9067486 | C5: =IFERROR('Raw Data - BS'!C20/'Raw Data - BS'!C11,0) -> 2.5574367 | D5: =IFERROR('Raw Data - BS'!D20/'Raw Data - BS'!D11,0) -> 2.5315671 | E5: =IFERROR('Raw Data - BS'!E20/'Raw Data - BS'!E11,0) -> 2.4506334 | F5: =IFERROR('Raw Data - BS'!F20/'Raw Data - BS'!F11,0) -> 2.3209185
A6: Quick Ratio | B6: =('Raw Data - BS'!B16 + 'Raw Data - BS'!B17) / 'Raw Data - BS'!B11 -> 1.14929 | C6: =('Raw Data - BS'!C16 + 'Raw Data - BS'!C17) / 'Raw Data - BS'!C11 -> 1.2328871 | D6: =('Raw Data - BS'!D16 + 'Raw Data - BS'!D17) / 'Raw Data - BS'!D11 -> 1.1833647 | E6: =('Raw Data - BS'!E16 + 'Raw Data - BS'!E17) / 'Raw Data - BS'!E11 -> 1.2444907 | F6: =('Raw Data - BS'!F16 + 'Raw Data - BS'!F17) / 'Raw Data - BS'!F11 -> 1.2224298
A8: PROFITABILITY RATIOS
A9: Net Profit Margin | B9: =IFERROR('Raw Data - PL'!B16/'Raw Data - PL'!B4,0) -> 0.20336588 | C9: =IFERROR('Raw Data - PL'!C16/'Raw Data - PL'!C4,0) -> 0.19987588 | D9: =IFERROR('Raw Data - PL'!D16/'Raw Data - PL'!D4,0) -> 0.18693947 | E9: =IFERROR('Raw Data - PL'!E16/'Raw Data - PL'!E4,0) -> 0.19338461 | F9: =IFERROR('Raw Data - PL'!F16/'Raw Data - PL'!F4,0) -> 0.1901623
A10: EBITDA Margin | B10: =IFERROR('Raw Data - PL'!B10/'Raw Data - PL'!B4,0) -> 0.28351109 | C10: =IFERROR('Raw Data - PL'!C10/'Raw Data - PL'!C4,0) -> 0.27669305 | D10: =IFERROR('Raw Data - PL'!D10/'Raw Data - PL'!D4,0) -> 0.26284275 | E10: =IFERROR('Raw Data - PL'!E10/'Raw Data - PL'!E4,0) -> 0.26690273 | F10: =IFERROR('Raw Data - PL'!F10/'Raw Data - PL'!F4,0) -> 0.26400573
A11: Return on Equity (ROE) | B11: =IFERROR('Raw Data - PL'!B16/'Raw Data - BS'!B6,0) -> 0.37417909 | C11: =IFERROR('Raw Data - PL'!C16/'Raw Data - BS'!C6,0) -> 0.41675184 | D11: =IFERROR('Raw Data - PL'!D16/'Raw Data - BS'!D6,0) -> 0.45162016 | E11: =IFERROR('Raw Data - PL'!E16/'Raw Data - BS'!E6,0) -> 0.49854455 | F11: =IFERROR('Raw Data - PL'!F16/'Raw Data - BS'!F6,0) -> 0.49596004
A12: Return on Assets (ROA) | B12: =IFERROR('Raw Data - PL'!B16/'Raw Data - BS'!B21,0) -> 0.25126241 | C12: =IFERROR('Raw Data - PL'!C16/'Raw Data - BS'!C21,0) -> 0.26683794 | D12: =IFERROR('Raw Data - PL'!D16/'Raw Data - BS'!D21,0) -> 0.28913555 | E12: =IFERROR('Raw Data - PL'!E16/'Raw Data - BS'!E21,0) -> 0.31355168 | F12: =IFERROR('Raw Data - PL'!F16/'Raw Data - BS'!F21,0) -> 0.30016383
A14: SOLVENCY RATIOS
A15: Debt-to-Equity Ratio | B15: =IFERROR('Raw Data - BS'!B12/'Raw Data - BS'!B6,0) -> 0.072879077 | C15: =IFERROR('Raw Data - BS'!C12/'Raw Data - BS'!C6,0) -> 0.069242981 | D15: =IFERROR('Raw Data - BS'!D12/'Raw Data - BS'!D6,0) -> 0.066467361 | E15: =IFERROR('Raw Data - BS'!E12/'Raw Data - BS'!E6,0) -> 0.069733096 | F15: =IFERROR('Raw Data - BS'!F12/'Raw Data - BS'!F6,0) -> 0.08006374
A16: Interest Coverage Ratio | B16: =IFERROR('Raw Data - PL'!B12/'Raw Data - PL'!B13,0) -> 0 | C16: =IFERROR('Raw Data - PL'!C12/'Raw Data - PL'!C13,0) -> 0 | D16: =IFERROR('Raw Data - PL'!D12/'Raw Data - PL'!D13,0) -> 0 | E16: =IFERROR('Raw Data - PL'!E12/'Raw Data - PL'!E13,0) -> 0 | F16: =IFERROR('Raw Data - PL'!F12/'Raw Data - PL'!F13,0) -> 0
A18: EFFICIENCY RATIOS
A19: Asset Turnover Ratio | B19: =IFERROR('Raw Data - PL'!B4/'Raw Data - BS'!B21,0) -> 1.235519 | C19: =IFERROR('Raw Data - PL'!C4/'Raw Data - BS'!C21,0) -> 1.3350182 | D19: =IFERROR('Raw Data - PL'!D4/'Raw Data - BS'!D21,0) -> 1.54668 | E19: =IFERROR('Raw Data - PL'!E4/'Raw Data - BS'!E21,0) -> 1.621389 | F19: =IFERROR('Raw Data - PL'!F4/'Raw Data - BS'!F21,0) -> 1.5784613
A20: Inventory Turnover Ratio | B20: =IFERROR('Raw Data - PL'!B4/'Raw Data - BS'!B18,0) -> 0 | C20: =IFERROR('Raw Data - PL'!C4/'Raw Data - BS'!C18,0) -> 0 | D20: =IFERROR('Raw Data - PL'!D4/'Raw Data - BS'!D18,0) -> 0 | E20: =IFERROR('Raw Data - PL'!E4/'Raw Data - BS'!E18,0) -> 0 | F20: =IFERROR('Raw Data - PL'!F4/'Raw Data - BS'!F18,0) -> 0
A21: Receivables Turnover Ratio | B21: =IFERROR('Raw Data - PL'!B4/'Raw Data - BS'!B17,0) -> 5.4482312 | C21: =IFERROR('Raw Data - PL'!C4/'Raw Data - BS'!C17,0) -> 5.6037289 | D21: =IFERROR('Raw Data - PL'!D4/'Raw Data - BS'!D17,0) -> 5.4725472 | E21: =IFERROR('Raw Data - PL'!E4/'Raw Data - BS'!E17,0) -> 5.4059155 | F21: =IFERROR('Raw Data - PL'!F4/'Raw Data - BS'!F17,0) -> 5.0827942

Sheet Trend Analysis
A1: Trend Analysis
A3: Metric | B3: FY21 | C3: FY22 | D3: FY23 | E3: FY24 | F3: FY25
A4: HORIZONTAL ANALYSIS (YoY GROWTH %)
A5: Revenue Growth % | B5: n/a — base year | C5: =IFERROR(('Raw Data - PL'!C4-'Raw Data - PL'!B4)/'Raw Data - PL'!B4,0) -> 0.16797115 | D5: =IFERROR(('Raw Data - PL'!D4-'Raw Data - PL'!C4)/'Raw Data - PL'!C4,0) -> 0.17576687 | E5: =IFERROR(('Raw Data - PL'!E4-'Raw Data - PL'!D4)/'Raw Data - PL'!D4,0) -> 0.068460645 | F5: =IFERROR(('Raw Data - PL'!F4-'Raw Data - PL'!E4)/'Raw Data - PL'!E4,0) -> 0.059906265
A6: EBITDA Growth % | B6: n/a — base year | C6: =IFERROR(('Raw Data - PL'!C10-'Raw Data - PL'!B10)/'Raw Data - PL'!B10,0) -> 0.13988313 | D6: =IFERROR(('Raw Data - PL'!D10-'Raw Data - PL'!C10)/'Raw Data - PL'!C10,0) -> 0.116912 | E6: =IFERROR(('Raw Data - PL'!E10-'Raw Data - PL'!D10)/'Raw Data - PL'!D10,0) -> 0.084964563 | F6: =IFERROR(('Raw Data - PL'!F10-'Raw Data - PL'!E10)/'Raw Data - PL'!E10,0) -> 0.048401898
A7: PAT Growth % | B7: n/a — base year | C7: =IFERROR(('Raw Data - PL'!C16-'Raw Data - PL'!B16)/'Raw Data - PL'!B16,0) -> 0.1479274 | D7: =IFERROR(('Raw Data - PL'!D16-'Raw Data - PL'!C16)/'Raw Data - PL'!C16,0) -> 0.099668641 | E7: =IFERROR(('Raw Data - PL'!E16-'Raw Data - PL'!D16)/'Raw Data - PL'!D16,0) -> 0.10529812 | F7: =IFERROR(('Raw Data - PL'!F16-'Raw Data - PL'!E16)/'Raw Data - PL'!E16,0) -> 0.042245358
A8: Total Assets Growth % | B8: n/a — base year | C8: =IFERROR(('Raw Data - BS'!C21-'Raw Data - BS'!B21)/'Raw Data - BS'!B21,0) -> 0.080922028 | D8: =IFERROR(('Raw Data - BS'!D21-'Raw Data - BS'!C21)/'Raw Data - BS'!C21,0) -> 0.014864169 | E8: =IFERROR(('Raw Data - BS'!E21-'Raw Data - BS'!D21)/'Raw Data - BS'!D21,0) -> 0.019229054 | F8: =IFERROR(('Raw Data - BS'!F21-'Raw Data - BS'!E21)/'Raw Data - BS'!E21,0) -> 0.088731389
A10: VERTICAL ANALYSIS (% OF REVENUE)
A11: Total Operating Expenses % of Revenue | B11: =IFERROR('Raw Data - PL'!B9/'Raw Data - PL'!B4,0) -> 0.74124877 | C11: =IFERROR('Raw Data - PL'!C9/'Raw Data - PL'!C4,0) -> 0.74731687 | D11: =IFERROR('Raw Data - PL'!D9/'Raw Data - PL'!D4,0) -> 0.75943635 | E11: =IFERROR('Raw Data - PL'!E9/'Raw Data - PL'!E4,0) -> 0.75378695 | F11: =IFERROR('Raw Data - PL'!F9/'Raw Data - PL'!F4,0) -> 0.75652504
A12: EBITDA % of Revenue | B12: =IFERROR('Raw Data - PL'!B10/'Raw Data - PL'!B4,0) -> 0.28351109 | C12: =IFERROR('Raw Data - PL'!C10/'Raw Data - PL'!C4,0) -> 0.27669305 | D12: =IFERROR('Raw Data - PL'!D10/'Raw Data - PL'!D4,0) -> 0.26284275 | E12: =IFERROR('Raw Data - PL'!E10/'Raw Data - PL'!E4,0) -> 0.26690273 | F12: =IFERROR('Raw Data - PL'!F10/'Raw Data - PL'!F4,0) -> 0.26400573
A13: EBIT % of Revenue | B13: =IFERROR('Raw Data - PL'!B12/'Raw Data - PL'!B4,0) -> 0.25875123 | C13: =IFERROR('Raw Data - PL'!C12/'Raw Data - PL'!C4,0) -> 0.25268313 | D13: =IFERROR('Raw Data - PL'!D12/'Raw Data - PL'!D4,0) -> 0.24056365 | E13: =IFERROR('Raw Data - PL'!E12/'Raw Data - PL'!E4,0) -> 0.24621305 | F13: =IFERROR('Raw Data - PL'!F12/'Raw Data - PL'!F4,0) -> 0.24347496
A14: PAT % of Revenue | B14: =IFERROR('Raw Data - PL'!B16/'Raw Data - PL'!B4,0) -> 0.20336588 | C14: =IFERROR('Raw Data - PL'!C16/'Raw Data - PL'!C4,0) -> 0.19987588 | D14: =IFERROR('Raw Data - PL'!D16/'Raw Data - PL'!D4,0) -> 0.18693947 | E14: =IFERROR('Raw Data - PL'!E16/'Raw Data - PL'!E4,0) -> 0.19338461 | F14: =IFERROR('Raw Data - PL'!F16/'Raw Data - PL'!F4,0) -> 0.1901623

Sheet Insights
A1: Management Insight Summary
A3: area | B3: Insight
A4: Revenue & Growth | B4: Revenue grew from ₹1,64,177 Cr (FY21) to ₹2,55,324 Cr (FY25), a ~55% increase over 5 years — though growth slowed from ~17% YoY (FY22-23) to ~6% (FY24-25), reflecting a maturing IT services demand environment.
A5: Profitability | B5: Net Profit Margin stayed strong (~19-20%) despite slowing growth, and ROE improved significantly from 37.4% to 49.6%, showing efficient use of shareholder capital.
A6: Liquidity Position | B6: Current Ratio declined from 2.91x to 2.32x — still comfortably above 1x, indicating strong short-term solvency, though liquidity buffer has thinned slightly.
A7: Solvency / Leverage | B7: Debt-to-Equity remained below 0.1x throughout FY21-25, showing TCS operates with virtually no financial leverage — a hallmark of asset-light IT services companies.
A8: Efficiency | B8: Asset Turnover improved from 1.24x to 1.58x, meaning TCS generates more revenue per rupee of assets over time — a sign of improving operational efficiency.
A9: Overall Investment View | B9: TCS shows a financially healthy, low-risk profile — strong margins, near-zero debt, and improving efficiency — though revenue growth has decelerated, a trend worth monitoring going forward.
