Workbook

Sheet Summary
A1: GSTR-2B vs Books ITC Reconciliation - Summary (April 2026)
A2: Nexus Tech Distribution Pvt. Ltd. | Tally Prime + Excel | All figures in Rs, dummy data for practice
A4: Status | B4: No. of Invoices | C4: Books Tax (Rs) | D4: 2B Tax (Rs) | E4: ITC Eligible (Rs) | F4: ITC on Hold / Not Claimable (Rs)
A5: Fully Matched | B5: =COUNTIF(ITC_Recon!$K$7:$K$11,$A5) -> 2 | C5: =SUMIF(ITC_Recon!$K$7:$K$11,$A5,ITC_Recon!$E$7:$E$11) -> 54000 | D5: =SUMIF(ITC_Recon!$K$7:$K$11,$A5,ITC_Recon!$H$7:$H$11) -> 54000 | E5: =SUMIF(ITC_Recon!$K$7:$K$11,$A5,ITC_Recon!$L$7:$L$11) -> 54000 | F5: =SUMIF(ITC_Recon!$K$7:$K$11,$A5,ITC_Recon!$M$7:$M$11) -> 0
A6: Tax Mismatch | B6: =COUNTIF(ITC_Recon!$K$7:$K$11,$A6) -> 0 | C6: =SUMIF(ITC_Recon!$K$7:$K$11,$A6,ITC_Recon!$E$7:$E$11) -> 0 | D6: =SUMIF(ITC_Recon!$K$7:$K$11,$A6,ITC_Recon!$H$7:$H$11) -> 0 | E6: =SUMIF(ITC_Recon!$K$7:$K$11,$A6,ITC_Recon!$L$7:$L$11) -> 0 | F6: =SUMIF(ITC_Recon!$K$7:$K$11,$A6,ITC_Recon!$M$7:$M$11) -> 0
A7: In Books, Missing in 2B | B7: =COUNTIF(ITC_Recon!$K$7:$K$11,$A7) -> 0 | C7: =SUMIF(ITC_Recon!$K$7:$K$11,$A7,ITC_Recon!$E$7:$E$11) -> 0 | D7: =SUMIF(ITC_Recon!$K$7:$K$11,$A7,ITC_Recon!$H$7:$H$11) -> 0 | E7: =SUMIF(ITC_Recon!$K$7:$K$11,$A7,ITC_Recon!$L$7:$L$11) -> 0 | F7: =SUMIF(ITC_Recon!$K$7:$K$11,$A7,ITC_Recon!$M$7:$M$11) -> 0
A8: In 2B, Missing in Books | B8: =COUNTIF(ITC_Recon!$K$17:$K$21,$A8) -> 0 | C8: 0 | D8: =SUMIF(ITC_Recon!$K$17:$K$21,$A8,ITC_Recon!$E$17:$E$21) -> 0 | E8: 0 | F8: =SUMIF(ITC_Recon!$K$17:$K$21,$A8,ITC_Recon!$M$17:$M$21) -> 0
A9: TOTAL | B9: =SUM(B5:B8) -> 2 | C9: =SUM(C5:C8) -> 54000 | D9: =SUM(D5:D8) -> 54000 | E9: =SUM(E5:E8) -> 54000 | F9: =SUM(F5:F8) -> 0
A11: Checks
A12: Books ITC total (Books_PR) | B12: =Books_PR!J10 -> 54000
A13: Eligible + on hold (Section A) | B13: =ITC_Recon!L12+ITC_Recon!M12 -> 54000
A14: Difference (must be 0) | B14: =B12-B13 -> 0
A15: Books invoices count = Section A count | B15: =COUNTA(Books_PR!E5:E9)-SUM(B5:B7) -> 0
A17: GSTR-3B position
A18: Output tax liability | B18: =GSTR3B_Working!E5 -> 54000
A19: Eligible ITC claimed | B19: =GSTR3B_Working!E6 -> 54000
A20: Tax payable in cash | B20: =GSTR3B_Working!E23 -> 0
A21: ITC carried forward | B21: =GSTR3B_Working!E24 -> 0
A23: Assumptions
A24: 1. Both purchase invoices and the sales figure are from the Nexus Tech Tally data. Invoice numbers are placeholders - replace with actual Tally references.
A25: 2. The GSTR-2B statement is a practice statement prepared to match the Tally invoices.
A26: 3. Vendor GSTINs are dummy numbers with valid check digits.
A27: 4. Note: matching with GSTR-2B is a reconciliation check; final ITC eligibility remains subject to applicable GST conditions and restrictions.
A28: 5. Tolerance of Rs 1 is used for matching (change in ITC_Recon!C3).
A29: 6. ITC treatment: Fully Matched = full ITC; Tax Mismatch = lower of Books/2B claimed; Missing in 2B = on hold; Missing in Books = claimed only after booking.
A30: 7. Blue text = input cells, green = links to other sheets, black = formulas.

Sheet Books_PR
A1: Books Purchase Register (Tally Prime export)
A2: Both invoices are from the Nexus Tech Tally purchase vouchers (amounts real; invoice nos. are placeholders - replace with the actual Tally reference).
A4: Sr | B4: Invoice Date | C4: Invoice No | D4: Vendor | E4: Vendor GSTIN | F4: Taxable Value | G4: CGST | H4: SGST | I4: IGST | J4: Total Tax | K4: Invoice Value | L4: Source | M4: Match Key (GSTIN|Invoice)
A5: 1 | B5: 46113 | C5: DS/26-27/001 | D5: Delta Systems Pvt Ltd | E5: 21AAACD4521M1Z0 | F5: 100000 | G5: 9000 | H5: 9000 | I5: 0 | J5: =IF(E5="","",G5+H5+I5) -> 18000 | K5: =IF(E5="","",F5+J5) -> 118000 | L5: Tally (Purch Vch 1) | M5: =IF(E5="","",E5&"|"&C5) -> 21AAACD4521M1Z0|DS/26-27/001
A6: 2 | B6: 46113 | C6: GTT/26-27/001 | D6: Global Tech Traders | E6: 19AAACG7789R1ZG | F6: 200000 | G6: 0 | H6: 0 | I6: 36000 | J6: =IF(E6="","",G6+H6+I6) -> 36000 | K6: =IF(E6="","",F6+J6) -> 236000 | L6: Tally (Purch Vch 2) | M6: =IF(E6="","",E6&"|"&C6) -> 19AAACG7789R1ZG|GTT/26-27/001
A7: 3 | J7: =IF(E7="","",G7+H7+I7) | K7: =IF(E7="","",F7+J7) | M7: =IF(E7="","",E7&"|"&C7)
A8: 4 | J8: =IF(E8="","",G8+H8+I8) | K8: =IF(E8="","",F8+J8) | M8: =IF(E8="","",E8&"|"&C8)
A9: 5 | J9: =IF(E9="","",G9+H9+I9) | K9: =IF(E9="","",F9+J9) | M9: =IF(E9="","",E9&"|"&C9)
D10: TOTAL | F10: =SUM(F5:F9) -> 300000 | G10: =SUM(G5:G9) -> 9000 | H10: =SUM(H5:H9) -> 9000 | I10: =SUM(I5:I9) -> 36000 | J10: =SUM(J5:J9) -> 54000 | K10: =SUM(K5:K9) -> 354000
A12: Legend: blue text = input cells (edit these). Black = formulas. Rows 5-9 hold up to 5 invoices; blank rows are ignored.

Sheet GSTR2B
A1: GSTR-2B Statement (dummy, as downloaded from GST portal)
A2: Practice statement in portal format, prepared to match the Tally invoices. Replace with the real GSTR-2B export when using actual data.
A4: Sr | B4: Invoice Date | C4: Invoice No | D4: Vendor | E4: Vendor GSTIN | F4: Taxable Value | G4: CGST | H4: SGST | I4: IGST | J4: Total Tax | K4: Invoice Value | L4: Source | M4: Match Key (GSTIN|Invoice)
A5: 1 | B5: 46113 | C5: DS/26-27/001 | D5: Delta Systems Pvt Ltd | E5: 21AAACD4521M1Z0 | F5: 100000 | G5: 9000 | H5: 9000 | I5: 0 | J5: =IF(E5="","",G5+H5+I5) -> 18000 | K5: =IF(E5="","",F5+J5) -> 118000 | L5: GSTR-2B (dummy) | M5: =IF(E5="","",E5&"|"&C5) -> 21AAACD4521M1Z0|DS/26-27/001
A6: 2 | B6: 46113 | C6: GTT/26-27/001 | D6: Global Tech Traders | E6: 19AAACG7789R1ZG | F6: 200000 | G6: 0 | H6: 0 | I6: 36000 | J6: =IF(E6="","",G6+H6+I6) -> 36000 | K6: =IF(E6="","",F6+J6) -> 236000 | L6: GSTR-2B (dummy) | M6: =IF(E6="","",E6&"|"&C6) -> 19AAACG7789R1ZG|GTT/26-27/001
A7: 3 | J7: =IF(E7="","",G7+H7+I7) | K7: =IF(E7="","",F7+J7) | M7: =IF(E7="","",E7&"|"&C7)
A8: 4 | J8: =IF(E8="","",G8+H8+I8) | K8: =IF(E8="","",F8+J8) | M8: =IF(E8="","",E8&"|"&C8)
A9: 5 | J9: =IF(E9="","",G9+H9+I9) | K9: =IF(E9="","",F9+J9) | M9: =IF(E9="","",E9&"|"&C9)
D10: TOTAL | F10: =SUM(F5:F9) -> 300000 | G10: =SUM(G5:G9) -> 9000 | H10: =SUM(H5:H9) -> 9000 | I10: =SUM(I5:I9) -> 36000 | J10: =SUM(J5:J9) -> 54000 | K10: =SUM(K5:K9) -> 354000
A12: Legend: blue text = input cells (edit these). Black = formulas. Rows 5-9 hold up to 5 invoices; blank rows are ignored.

Sheet ITC_Recon
A1: GSTR-2B vs Books ITC Reconciliation - April 2026
A2: Match is done on Vendor GSTIN + Invoice No. (INDEX/MATCH on helper key, works in all Excel versions).
A3: Tolerance (Rs) | C3: 1 | D3: Differences up to this amount are treated as a match (assumption).
A5: SECTION A: Invoices recorded in Books (compared with GSTR-2B)
A6: Sr | B6: Invoice No | C6: Vendor | D6: Books Taxable | E6: Books Tax | F6: In 2B? | G6: 2B Taxable | H6: 2B Tax | I6: Taxable Diff | J6: Tax Diff | K6: Status | L6: ITC Eligible | M6: ITC on Hold | N6: Action | O6: Eligible CGST | P6: Eligible SGST | Q6: Eligible IGST
A7: =IF(Books_PR!E5="","",ROW()-6) -> 1 | B7: =IF($A7="","",Books_PR!C5) -> DS/26-27/001 | C7: =IF($A7="","",Books_PR!D5) -> Delta Systems Pvt Ltd | D7: =IF($A7="","",Books_PR!F5) -> 100000 | E7: =IF($A7="","",Books_PR!J5) -> 18000 | F7: =IF($A7="","",IF(ISNUMBER(MATCH(Books_PR!M5,GSTR2B!$M$5:$M$9,0)),"Yes","No")) -> Yes | G7: =IF($A7="","",IF(F7="Yes",INDEX(GSTR2B!$F$5:$F$9,MATCH(Books_PR!M5,GSTR2B!$M$5:$M$9,0)),0)) -> 100000 | H7: =IF($A7="","",IF(F7="Yes",INDEX(GSTR2B!$J$5:$J$9,MATCH(Books_PR!M5,GSTR2B!$M$5:$M$9,0)),0)) -> 18000 | I7: =IF($A7="","",D7-G7) -> 0 | J7: =IF($A7="","",E7-H7) -> 0 | K7: =IF($A7="","",IF(F7="No","In Books, Missing in 2B",IF(AND(ABS(I7)<=$C$3,ABS(J7)<=$C$3),"Fully Matched","Tax Mismatch"))) -> Fully Matched | L7: =IF($A7="","",IF(K7="Fully Matched",E7,IF(K7="Tax Mismatch",MIN(E7,H7),0))) -> 18000 | M7: =IF($A7="","",E7-L7) -> 0 | N7: =IF($A7="","",IF(K7="Fully Matched","Claim ITC",IF(K7="Tax Mismatch","Claim lower of Books and 2B; ask vendor to amend GSTR-1","Hold ITC until vendor files GSTR-1"))) -> Claim ITC | O7: =IF($A7="","",IF($E7=0,0,Books_PR!G5*$L7/$E7)) -> 9000 | P7: =IF($A7="","",IF($E7=0,0,Books_PR!H5*$L7/$E7)) -> 9000 | Q7: =IF($A7="","",IF($E7=0,0,Books_PR!I5*$L7/$E7)) -> 0
A8: =IF(Books_PR!E6="","",ROW()-6) -> 2 | B8: =IF($A8="","",Books_PR!C6) -> GTT/26-27/001 | C8: =IF($A8="","",Books_PR!D6) -> Global Tech Traders | D8: =IF($A8="","",Books_PR!F6) -> 200000 | E8: =IF($A8="","",Books_PR!J6) -> 36000 | F8: =IF($A8="","",IF(ISNUMBER(MATCH(Books_PR!M6,GSTR2B!$M$5:$M$9,0)),"Yes","No")) -> Yes | G8: =IF($A8="","",IF(F8="Yes",INDEX(GSTR2B!$F$5:$F$9,MATCH(Books_PR!M6,GSTR2B!$M$5:$M$9,0)),0)) -> 200000 | H8: =IF($A8="","",IF(F8="Yes",INDEX(GSTR2B!$J$5:$J$9,MATCH(Books_PR!M6,GSTR2B!$M$5:$M$9,0)),0)) -> 36000 | I8: =IF($A8="","",D8-G8) -> 0 | J8: =IF($A8="","",E8-H8) -> 0 | K8: =IF($A8="","",IF(F8="No","In Books, Missing in 2B",IF(AND(ABS(I8)<=$C$3,ABS(J8)<=$C$3),"Fully Matched","Tax Mismatch"))) -> Fully Matched | L8: =IF($A8="","",IF(K8="Fully Matched",E8,IF(K8="Tax Mismatch",MIN(E8,H8),0))) -> 36000 | M8: =IF($A8="","",E8-L8) -> 0 | N8: =IF($A8="","",IF(K8="Fully Matched","Claim ITC",IF(K8="Tax Mismatch","Claim lower of Books and 2B; ask vendor to amend GSTR-1","Hold ITC until vendor files GSTR-1"))) -> Claim ITC | O8: =IF($A8="","",IF($E8=0,0,Books_PR!G6*$L8/$E8)) -> 0 | P8: =IF($A8="","",IF($E8=0,0,Books_PR!H6*$L8/$E8)) -> 0 | Q8: =IF($A8="","",IF($E8=0,0,Books_PR!I6*$L8/$E8)) -> 36000
A9: =IF(Books_PR!E7="","",ROW()-6) | B9: =IF($A9="","",Books_PR!C7) | C9: =IF($A9="","",Books_PR!D7) | D9: =IF($A9="","",Books_PR!F7) | E9: =IF($A9="","",Books_PR!J7) | F9: =IF($A9="","",IF(ISNUMBER(MATCH(Books_PR!M7,GSTR2B!$M$5:$M$9,0)),"Yes","No")) | G9: =IF($A9="","",IF(F9="Yes",INDEX(GSTR2B!$F$5:$F$9,MATCH(Books_PR!M7,GSTR2B!$M$5:$M$9,0)),0)) | H9: =IF($A9="","",IF(F9="Yes",INDEX(GSTR2B!$J$5:$J$9,MATCH(Books_PR!M7,GSTR2B!$M$5:$M$9,0)),0)) | I9: =IF($A9="","",D9-G9) | J9: =IF($A9="","",E9-H9) | K9: =IF($A9="","",IF(F9="No","In Books, Missing in 2B",IF(AND(ABS(I9)<=$C$3,ABS(J9)<=$C$3),"Fully Matched","Tax Mismatch"))) | L9: =IF($A9="","",IF(K9="Fully Matched",E9,IF(K9="Tax Mismatch",MIN(E9,H9),0))) | M9: =IF($A9="","",E9-L9) | N9: =IF($A9="","",IF(K9="Fully Matched","Claim ITC",IF(K9="Tax Mismatch","Claim lower of Books and 2B; ask vendor to amend GSTR-1","Hold ITC until vendor files GSTR-1"))) | O9: =IF($A9="","",IF($E9=0,0,Books_PR!G7*$L9/$E9)) | P9: =IF($A9="","",IF($E9=0,0,Books_PR!H7*$L9/$E9)) | Q9: =IF($A9="","",IF($E9=0,0,Books_PR!I7*$L9/$E9))
A10: =IF(Books_PR!E8="","",ROW()-6) | B10: =IF($A10="","",Books_PR!C8) | C10: =IF($A10="","",Books_PR!D8) | D10: =IF($A10="","",Books_PR!F8) | E10: =IF($A10="","",Books_PR!J8) | F10: =IF($A10="","",IF(ISNUMBER(MATCH(Books_PR!M8,GSTR2B!$M$5:$M$9,0)),"Yes","No")) | G10: =IF($A10="","",IF(F10="Yes",INDEX(GSTR2B!$F$5:$F$9,MATCH(Books_PR!M8,GSTR2B!$M$5:$M$9,0)),0)) | H10: =IF($A10="","",IF(F10="Yes",INDEX(GSTR2B!$J$5:$J$9,MATCH(Books_PR!M8,GSTR2B!$M$5:$M$9,0)),0)) | I10: =IF($A10="","",D10-G10) | J10: =IF($A10="","",E10-H10) | K10: =IF($A10="","",IF(F10="No","In Books, Missing in 2B",IF(AND(ABS(I10)<=$C$3,ABS(J10)<=$C$3),"Fully Matched","Tax Mismatch"))) | L10: =IF($A10="","",IF(K10="Fully Matched",E10,IF(K10="Tax Mismatch",MIN(E10,H10),0))) | M10: =IF($A10="","",E10-L10) | N10: =IF($A10="","",IF(K10="Fully Matched","Claim ITC",IF(K10="Tax Mismatch","Claim lower of Books and 2B; ask vendor to amend GSTR-1","Hold ITC until vendor files GSTR-1"))) | O10: =IF($A10="","",IF($E10=0,0,Books_PR!G8*$L10/$E10)) | P10: =IF($A10="","",IF($E10=0,0,Books_PR!H8*$L10/$E10)) | Q10: =IF($A10="","",IF($E10=0,0,Books_PR!I8*$L10/$E10))
A11: =IF(Books_PR!E9="","",ROW()-6) | B11: =IF($A11="","",Books_PR!C9) | C11: =IF($A11="","",Books_PR!D9) | D11: =IF($A11="","",Books_PR!F9) | E11: =IF($A11="","",Books_PR!J9) | F11: =IF($A11="","",IF(ISNUMBER(MATCH(Books_PR!M9,GSTR2B!$M$5:$M$9,0)),"Yes","No")) | G11: =IF($A11="","",IF(F11="Yes",INDEX(GSTR2B!$F$5:$F$9,MATCH(Books_PR!M9,GSTR2B!$M$5:$M$9,0)),0)) | H11: =IF($A11="","",IF(F11="Yes",INDEX(GSTR2B!$J$5:$J$9,MATCH(Books_PR!M9,GSTR2B!$M$5:$M$9,0)),0)) | I11: =IF($A11="","",D11-G11) | J11: =IF($A11="","",E11-H11) | K11: =IF($A11="","",IF(F11="No","In Books, Missing in 2B",IF(AND(ABS(I11)<=$C$3,ABS(J11)<=$C$3),"Fully Matched","Tax Mismatch"))) | L11: =IF($A11="","",IF(K11="Fully Matched",E11,IF(K11="Tax Mismatch",MIN(E11,H11),0))) | M11: =IF($A11="","",E11-L11) | N11: =IF($A11="","",IF(K11="Fully Matched","Claim ITC",IF(K11="Tax Mismatch","Claim lower of Books and 2B; ask vendor to amend GSTR-1","Hold ITC until vendor files GSTR-1"))) | O11: =IF($A11="","",IF($E11=0,0,Books_PR!G9*$L11/$E11)) | P11: =IF($A11="","",IF($E11=0,0,Books_PR!H9*$L11/$E11)) | Q11: =IF($A11="","",IF($E11=0,0,Books_PR!I9*$L11/$E11))
C12: TOTAL | D12: =SUM(D7:D11) -> 300000 | E12: =SUM(E7:E11) -> 54000 | G12: =SUM(G7:G11) -> 300000 | H12: =SUM(H7:H11) -> 54000 | I12: =SUM(I7:I11) -> 0 | J12: =SUM(J7:J11) -> 0 | L12: =SUM(L7:L11) -> 54000 | M12: =SUM(M7:M11) -> 0 | O12: =SUM(O7:O11) -> 9000 | P12: =SUM(P7:P11) -> 9000 | Q12: =SUM(Q7:Q11) -> 36000
A15: SECTION B: Invoices in GSTR-2B but NOT in Books
A16: Sr | B16: Invoice No | C16: Vendor | D16: 2B Taxable | E16: 2B Tax | F16: In Books? | K16: Status | L16: ITC Eligible | M16: ITC Not Claimable | N16: Action
A17: =IF(GSTR2B!E5="","",ROW()-16) -> 1 | B17: =IF($A17="","",GSTR2B!C5) -> DS/26-27/001 | C17: =IF($A17="","",GSTR2B!D5) -> Delta Systems Pvt Ltd | D17: =IF($A17="","",GSTR2B!F5) -> 100000 | E17: =IF($A17="","",GSTR2B!J5) -> 18000 | F17: =IF($A17="","",IF(ISNUMBER(MATCH(GSTR2B!M5,Books_PR!$M$5:$M$9,0)),"Yes","No")) -> Yes | K17: =IF($A17="","",IF(F17="No","In 2B, Missing in Books","Matched (see Section A)")) -> Matched (see Section A) | L17: =IF($A17="","",0) -> 0 | M17: =IF($A17="","",IF(F17="No",E17,0)) -> 0 | N17: =IF($A17="","",IF(F17="No","Check if invoice was missed in accounting; book it, then claim ITC",""))
A18: =IF(GSTR2B!E6="","",ROW()-16) -> 2 | B18: =IF($A18="","",GSTR2B!C6) -> GTT/26-27/001 | C18: =IF($A18="","",GSTR2B!D6) -> Global Tech Traders | D18: =IF($A18="","",GSTR2B!F6) -> 200000 | E18: =IF($A18="","",GSTR2B!J6) -> 36000 | F18: =IF($A18="","",IF(ISNUMBER(MATCH(GSTR2B!M6,Books_PR!$M$5:$M$9,0)),"Yes","No")) -> Yes | K18: =IF($A18="","",IF(F18="No","In 2B, Missing in Books","Matched (see Section A)")) -> Matched (see Section A) | L18: =IF($A18="","",0) -> 0 | M18: =IF($A18="","",IF(F18="No",E18,0)) -> 0 | N18: =IF($A18="","",IF(F18="No","Check if invoice was missed in accounting; book it, then claim ITC",""))
A19: =IF(GSTR2B!E7="","",ROW()-16) | B19: =IF($A19="","",GSTR2B!C7) | C19: =IF($A19="","",GSTR2B!D7) | D19: =IF($A19="","",GSTR2B!F7) | E19: =IF($A19="","",GSTR2B!J7) | F19: =IF($A19="","",IF(ISNUMBER(MATCH(GSTR2B!M7,Books_PR!$M$5:$M$9,0)),"Yes","No")) | K19: =IF($A19="","",IF(F19="No","In 2B, Missing in Books","Matched (see Section A)")) | L19: =IF($A19="","",0) | M19: =IF($A19="","",IF(F19="No",E19,0)) | N19: =IF($A19="","",IF(F19="No","Check if invoice was missed in accounting; book it, then claim ITC",""))
A20: =IF(GSTR2B!E8="","",ROW()-16) | B20: =IF($A20="","",GSTR2B!C8) | C20: =IF($A20="","",GSTR2B!D8) | D20: =IF($A20="","",GSTR2B!F8) | E20: =IF($A20="","",GSTR2B!J8) | F20: =IF($A20="","",IF(ISNUMBER(MATCH(GSTR2B!M8,Books_PR!$M$5:$M$9,0)),"Yes","No")) | K20: =IF($A20="","",IF(F20="No","In 2B, Missing in Books","Matched (see Section A)")) | L20: =IF($A20="","",0) | M20: =IF($A20="","",IF(F20="No",E20,0)) | N20: =IF($A20="","",IF(F20="No","Check if invoice was missed in accounting; book it, then claim ITC",""))
A21: =IF(GSTR2B!E9="","",ROW()-16) | B21: =IF($A21="","",GSTR2B!C9) | C21: =IF($A21="","",GSTR2B!D9) | D21: =IF($A21="","",GSTR2B!F9) | E21: =IF($A21="","",GSTR2B!J9) | F21: =IF($A21="","",IF(ISNUMBER(MATCH(GSTR2B!M9,Books_PR!$M$5:$M$9,0)),"Yes","No")) | K21: =IF($A21="","",IF(F21="No","In 2B, Missing in Books","Matched (see Section A)")) | L21: =IF($A21="","",0) | M21: =IF($A21="","",IF(F21="No",E21,0)) | N21: =IF($A21="","",IF(F21="No","Check if invoice was missed in accounting; book it, then claim ITC",""))
C22: TOTAL | D22: =SUM(D17:D21) -> 300000 | E22: =SUM(E17:E21) -> 54000 | L22: =SUM(L17:L21) -> 0 | M22: =SUM(M17:M21) -> 0
A24: ITC rule used (assumption): Fully Matched = full ITC; Tax Mismatch = lower of Books/2B claimed, excess on hold; Missing in 2B = nil, on hold; Missing in Books = not claimed until booked.

Sheet GSTR3B_Working
A1: GSTR-3B Tax Liability Working - April 2026
A2: Output tax from Tally Sales Register; ITC from ITC_Recon (eligible only). Set-off follows the GST order of utilisation.
A4: Particulars | B4: IGST | C4: CGST | D4: SGST / UTGST | E4: Total
A5: Output tax liability (Table 3.1) - Sales Vch No. 1, Infotech Solutions Ltd (taxable Rs 3,00,000 @18%) | B5: 0 | C5: 27000 | D5: 27000 | E5: =SUM(B5:D5) -> 54000
A6: Eligible ITC (Table 4C) - from ITC_Recon | B6: =ITC_Recon!Q12 -> 36000 | C6: =ITC_Recon!O12 -> 9000 | D6: =ITC_Recon!P12 -> 9000 | E6: =SUM(B6:D6) -> 54000
A7: ITC on hold (not claimed this month) | E7: =ITC_Recon!M12 -> 0
A9: Utilisation of ITC as per Rule 88A: IGST credit first (against IGST, then CGST and SGST in any order), and only then the CGST and SGST credit
A10: Set-off step | B10: Amount
A11: IGST credit used against IGST liability | B11: =MIN(B6,B5) -> 0
A12: IGST credit balance used against CGST liability | B12: =MIN(B6-B11,MAX(0,C5-C6)) -> 18000
A13: IGST credit balance used against SGST liability | B13: =MIN(B6-B11-B12,MAX(0,D5-D6)) -> 18000
A14: Remaining IGST credit used against CGST liability | B14: =MIN(B6-B11-B12-B13,C5-B12) -> 0
A15: Remaining IGST credit used against SGST liability | B15: =MIN(B6-B11-B12-B13-B14,D5-B13) -> 0
A16: CGST credit used against CGST liability (after IGST credit) | B16: =MIN(C6,C5-B12-B14) -> 9000
A17: SGST credit used against SGST liability (after IGST credit) | B17: =MIN(D6,D5-B13-B15) -> 9000
A18: CGST credit balance used against IGST liability | B18: =MIN(C6-B16,B5-B11) -> 0
A19: SGST credit balance used against IGST liability | B19: =MIN(D6-B17,B5-B11-B18) -> 0
A21: Net position
A22: Particulars | B22: IGST | C22: CGST | D22: SGST / UTGST | E22: Total
A23: Tax payable in cash (Table 6.1) | B23: =B5-B11-B18-B19 -> 0 | C23: =C5-B12-B14-B16 -> 0 | D23: =D5-B13-B15-B17 -> 0 | E23: =SUM(B23:D23) -> 0
A24: ITC balance carried forward | B24: =B6-B11-B12-B13-B14-B15 -> 0 | C24: =C6-B16-B18 -> 0 | D24: =D6-B17-B19 -> 0 | E24: =SUM(B24:D24) -> 0
A26: Check: output liability - ITC utilised - cash payable = 0 | B26: =E5-SUM(B11:B19)-E23 -> 0
A28: Note: Output tax (blue) is typed from the Tally Sales Register / GSTR-1 (Sales Vch No. 1). Update it if you add more sales vouchers.
