Workbook

Sheet Payroll_Master
A1: Payroll Master Sheet - April 2026
A2: Nexus Tech Distribution Pvt. Ltd. | Rs | Dummy employees. Blue = inputs (Basic, Special Allowance, LOP days); everything else is a formula.
A4: Sr | B4: Employee | C4: Designation | D4: Basic (Fixed) | E4: HRA (Fixed) | F4: Special Allowance (Fixed) | G4: Gross (Fixed) | H4: Days in Month | I4: LOP Days | J4: Days Paid | K4: Basic (Earned) | L4: HRA (Earned) | M4: Special Allow. (Earned) | N4: Gross (Earned) | O4: LOP Deduction | P4: PF - Employee | Q4: ESI - Employee | R4: TDS (Sec 392) | S4: Total Deductions | T4: Net Salary Payable | U4: PF - Employer | V4: ESI - Employer | W4: Total Cost to Company
A5: 1 | B5: Rakesh Sahoo | C5: Manager | D5: 70000 | E5: =IF($B5="","",ROUND(D5*Assumptions!$B$6,0)) -> 28000 | F5: 55000 | G5: =IF($B5="","",D5+E5+F5) -> 153000 | H5: =IF($B5="","",Assumptions!$B$5) -> 30 | I5: 0 | J5: =IF($B5="","",H5-I5) -> 30 | K5: =IF($B5="","",ROUND(D5*J5/H5,0)) -> 70000 | L5: =IF($B5="","",ROUND(E5*J5/H5,0)) -> 28000 | M5: =IF($B5="","",ROUND(F5*J5/H5,0)) -> 55000 | N5: =IF($B5="","",K5+L5+M5) -> 153000 | O5: =IF($B5="","",G5-N5) -> 0 | P5: =IF($B5="","",ROUND(Assumptions!$B$7*MIN(K5,Assumptions!$B$9),0)) -> 1800 | Q5: =IF($B5="","",IF(G5<=Assumptions!$B$10,ROUNDUP(N5*Assumptions!$B$11,0),0)) -> 0 | R5: =IF($B5="","",TDS_Working!K5) -> 13191 | S5: =IF($B5="","",P5+Q5+R5) -> 14991 | T5: =IF($B5="","",N5-S5) -> 138009 | U5: =IF($B5="","",ROUND(Assumptions!$B$8*MIN(K5,Assumptions!$B$9),0)) -> 1800 | V5: =IF($B5="","",IF(G5<=Assumptions!$B$10,ROUNDUP(N5*Assumptions!$B$12,0),0)) -> 0 | W5: =IF($B5="","",N5+U5+V5) -> 154800
A6: 2 | B6: Smita Mohanty | C6: Accounts Head | D6: 50000 | E6: =IF($B6="","",ROUND(D6*Assumptions!$B$6,0)) -> 20000 | F6: 40000 | G6: =IF($B6="","",D6+E6+F6) -> 110000 | H6: =IF($B6="","",Assumptions!$B$5) -> 30 | I6: 0 | J6: =IF($B6="","",H6-I6) -> 30 | K6: =IF($B6="","",ROUND(D6*J6/H6,0)) -> 50000 | L6: =IF($B6="","",ROUND(E6*J6/H6,0)) -> 20000 | M6: =IF($B6="","",ROUND(F6*J6/H6,0)) -> 40000 | N6: =IF($B6="","",K6+L6+M6) -> 110000 | O6: =IF($B6="","",G6-N6) -> 0 | P6: =IF($B6="","",ROUND(Assumptions!$B$7*MIN(K6,Assumptions!$B$9),0)) -> 1800 | Q6: =IF($B6="","",IF(G6<=Assumptions!$B$10,ROUNDUP(N6*Assumptions!$B$11,0),0)) -> 0 | R6: =IF($B6="","",TDS_Working!K6) -> 3900 | S6: =IF($B6="","",P6+Q6+R6) -> 5700 | T6: =IF($B6="","",N6-S6) -> 104300 | U6: =IF($B6="","",ROUND(Assumptions!$B$8*MIN(K6,Assumptions!$B$9),0)) -> 1800 | V6: =IF($B6="","",IF(G6<=Assumptions!$B$10,ROUNDUP(N6*Assumptions!$B$12,0),0)) -> 0 | W6: =IF($B6="","",N6+U6+V6) -> 111800
A7: 3 | B7: Prakash Nayak | C7: Sales Executive | D7: 25000 | E7: =IF($B7="","",ROUND(D7*Assumptions!$B$6,0)) -> 10000 | F7: 15000 | G7: =IF($B7="","",D7+E7+F7) -> 50000 | H7: =IF($B7="","",Assumptions!$B$5) -> 30 | I7: 2 | J7: =IF($B7="","",H7-I7) -> 28 | K7: =IF($B7="","",ROUND(D7*J7/H7,0)) -> 23333 | L7: =IF($B7="","",ROUND(E7*J7/H7,0)) -> 9333 | M7: =IF($B7="","",ROUND(F7*J7/H7,0)) -> 14000 | N7: =IF($B7="","",K7+L7+M7) -> 46666 | O7: =IF($B7="","",G7-N7) -> 3334 | P7: =IF($B7="","",ROUND(Assumptions!$B$7*MIN(K7,Assumptions!$B$9),0)) -> 1800 | Q7: =IF($B7="","",IF(G7<=Assumptions!$B$10,ROUNDUP(N7*Assumptions!$B$11,0),0)) -> 0 | R7: =IF($B7="","",TDS_Working!K7) -> 0 | S7: =IF($B7="","",P7+Q7+R7) -> 1800 | T7: =IF($B7="","",N7-S7) -> 44866 | U7: =IF($B7="","",ROUND(Assumptions!$B$8*MIN(K7,Assumptions!$B$9),0)) -> 1800 | V7: =IF($B7="","",IF(G7<=Assumptions!$B$10,ROUNDUP(N7*Assumptions!$B$12,0),0)) -> 0 | W7: =IF($B7="","",N7+U7+V7) -> 48466
A8: 4 | B8: Anita Das | C8: MIS Executive | D8: 22000 | E8: =IF($B8="","",ROUND(D8*Assumptions!$B$6,0)) -> 8800 | F8: 9200 | G8: =IF($B8="","",D8+E8+F8) -> 40000 | H8: =IF($B8="","",Assumptions!$B$5) -> 30 | I8: 0 | J8: =IF($B8="","",H8-I8) -> 30 | K8: =IF($B8="","",ROUND(D8*J8/H8,0)) -> 22000 | L8: =IF($B8="","",ROUND(E8*J8/H8,0)) -> 8800 | M8: =IF($B8="","",ROUND(F8*J8/H8,0)) -> 9200 | N8: =IF($B8="","",K8+L8+M8) -> 40000 | O8: =IF($B8="","",G8-N8) -> 0 | P8: =IF($B8="","",ROUND(Assumptions!$B$7*MIN(K8,Assumptions!$B$9),0)) -> 1800 | Q8: =IF($B8="","",IF(G8<=Assumptions!$B$10,ROUNDUP(N8*Assumptions!$B$11,0),0)) -> 0 | R8: =IF($B8="","",TDS_Working!K8) -> 0 | S8: =IF($B8="","",P8+Q8+R8) -> 1800 | T8: =IF($B8="","",N8-S8) -> 38200 | U8: =IF($B8="","",ROUND(Assumptions!$B$8*MIN(K8,Assumptions!$B$9),0)) -> 1800 | V8: =IF($B8="","",IF(G8<=Assumptions!$B$10,ROUNDUP(N8*Assumptions!$B$12,0),0)) -> 0 | W8: =IF($B8="","",N8+U8+V8) -> 41800
A9: 5 | B9: Sanjay Behera | C9: Tally Operator | D9: 18000 | E9: =IF($B9="","",ROUND(D9*Assumptions!$B$6,0)) -> 7200 | F9: 4800 | G9: =IF($B9="","",D9+E9+F9) -> 30000 | H9: =IF($B9="","",Assumptions!$B$5) -> 30 | I9: 1 | J9: =IF($B9="","",H9-I9) -> 29 | K9: =IF($B9="","",ROUND(D9*J9/H9,0)) -> 17400 | L9: =IF($B9="","",ROUND(E9*J9/H9,0)) -> 6960 | M9: =IF($B9="","",ROUND(F9*J9/H9,0)) -> 4640 | N9: =IF($B9="","",K9+L9+M9) -> 29000 | O9: =IF($B9="","",G9-N9) -> 1000 | P9: =IF($B9="","",ROUND(Assumptions!$B$7*MIN(K9,Assumptions!$B$9),0)) -> 1800 | Q9: =IF($B9="","",IF(G9<=Assumptions!$B$10,ROUNDUP(N9*Assumptions!$B$11,0),0)) -> 0 | R9: =IF($B9="","",TDS_Working!K9) -> 0 | S9: =IF($B9="","",P9+Q9+R9) -> 1800 | T9: =IF($B9="","",N9-S9) -> 27200 | U9: =IF($B9="","",ROUND(Assumptions!$B$8*MIN(K9,Assumptions!$B$9),0)) -> 1800 | V9: =IF($B9="","",IF(G9<=Assumptions!$B$10,ROUNDUP(N9*Assumptions!$B$12,0),0)) -> 0 | W9: =IF($B9="","",N9+U9+V9) -> 30800
A10: 6 | B10: Pooja Sharma | C10: Junior Accountant | D10: 16000 | E10: =IF($B10="","",ROUND(D10*Assumptions!$B$6,0)) -> 6400 | F10: 3600 | G10: =IF($B10="","",D10+E10+F10) -> 26000 | H10: =IF($B10="","",Assumptions!$B$5) -> 30 | I10: 0 | J10: =IF($B10="","",H10-I10) -> 30 | K10: =IF($B10="","",ROUND(D10*J10/H10,0)) -> 16000 | L10: =IF($B10="","",ROUND(E10*J10/H10,0)) -> 6400 | M10: =IF($B10="","",ROUND(F10*J10/H10,0)) -> 3600 | N10: =IF($B10="","",K10+L10+M10) -> 26000 | O10: =IF($B10="","",G10-N10) -> 0 | P10: =IF($B10="","",ROUND(Assumptions!$B$7*MIN(K10,Assumptions!$B$9),0)) -> 1800 | Q10: =IF($B10="","",IF(G10<=Assumptions!$B$10,ROUNDUP(N10*Assumptions!$B$11,0),0)) -> 0 | R10: =IF($B10="","",TDS_Working!K10) -> 0 | S10: =IF($B10="","",P10+Q10+R10) -> 1800 | T10: =IF($B10="","",N10-S10) -> 24200 | U10: =IF($B10="","",ROUND(Assumptions!$B$8*MIN(K10,Assumptions!$B$9),0)) -> 1800 | V10: =IF($B10="","",IF(G10<=Assumptions!$B$10,ROUNDUP(N10*Assumptions!$B$12,0),0)) -> 0 | W10: =IF($B10="","",N10+U10+V10) -> 27800
A11: 7 | B11: Ramesh Pradhan | C11: Store Assistant | D11: 10000 | E11: =IF($B11="","",ROUND(D11*Assumptions!$B$6,0)) -> 4000 | F11: 3000 | G11: =IF($B11="","",D11+E11+F11) -> 17000 | H11: =IF($B11="","",Assumptions!$B$5) -> 30 | I11: 3 | J11: =IF($B11="","",H11-I11) -> 27 | K11: =IF($B11="","",ROUND(D11*J11/H11,0)) -> 9000 | L11: =IF($B11="","",ROUND(E11*J11/H11,0)) -> 3600 | M11: =IF($B11="","",ROUND(F11*J11/H11,0)) -> 2700 | N11: =IF($B11="","",K11+L11+M11) -> 15300 | O11: =IF($B11="","",G11-N11) -> 1700 | P11: =IF($B11="","",ROUND(Assumptions!$B$7*MIN(K11,Assumptions!$B$9),0)) -> 1080 | Q11: =IF($B11="","",IF(G11<=Assumptions!$B$10,ROUNDUP(N11*Assumptions!$B$11,0),0)) -> 115 | R11: =IF($B11="","",TDS_Working!K11) -> 0 | S11: =IF($B11="","",P11+Q11+R11) -> 1195 | T11: =IF($B11="","",N11-S11) -> 14105 | U11: =IF($B11="","",ROUND(Assumptions!$B$8*MIN(K11,Assumptions!$B$9),0)) -> 1080 | V11: =IF($B11="","",IF(G11<=Assumptions!$B$10,ROUNDUP(N11*Assumptions!$B$12,0),0)) -> 498 | W11: =IF($B11="","",N11+U11+V11) -> 16878
A12: 8 | B12: Lata Munda | C12: Office Helper | D12: 8000 | E12: =IF($B12="","",ROUND(D12*Assumptions!$B$6,0)) -> 3200 | F12: 2300 | G12: =IF($B12="","",D12+E12+F12) -> 13500 | H12: =IF($B12="","",Assumptions!$B$5) -> 30 | I12: 0 | J12: =IF($B12="","",H12-I12) -> 30 | K12: =IF($B12="","",ROUND(D12*J12/H12,0)) -> 8000 | L12: =IF($B12="","",ROUND(E12*J12/H12,0)) -> 3200 | M12: =IF($B12="","",ROUND(F12*J12/H12,0)) -> 2300 | N12: =IF($B12="","",K12+L12+M12) -> 13500 | O12: =IF($B12="","",G12-N12) -> 0 | P12: =IF($B12="","",ROUND(Assumptions!$B$7*MIN(K12,Assumptions!$B$9),0)) -> 960 | Q12: =IF($B12="","",IF(G12<=Assumptions!$B$10,ROUNDUP(N12*Assumptions!$B$11,0),0)) -> 102 | R12: =IF($B12="","",TDS_Working!K12) -> 0 | S12: =IF($B12="","",P12+Q12+R12) -> 1062 | T12: =IF($B12="","",N12-S12) -> 12438 | U12: =IF($B12="","",ROUND(Assumptions!$B$8*MIN(K12,Assumptions!$B$9),0)) -> 960 | V12: =IF($B12="","",IF(G12<=Assumptions!$B$10,ROUNDUP(N12*Assumptions!$B$12,0),0)) -> 439 | W12: =IF($B12="","",N12+U12+V12) -> 14899
A13: 9 | E13: =IF($B13="","",ROUND(D13*Assumptions!$B$6,0)) | G13: =IF($B13="","",D13+E13+F13) | H13: =IF($B13="","",Assumptions!$B$5) | J13: =IF($B13="","",H13-I13) | K13: =IF($B13="","",ROUND(D13*J13/H13,0)) | L13: =IF($B13="","",ROUND(E13*J13/H13,0)) | M13: =IF($B13="","",ROUND(F13*J13/H13,0)) | N13: =IF($B13="","",K13+L13+M13) | O13: =IF($B13="","",G13-N13) | P13: =IF($B13="","",ROUND(Assumptions!$B$7*MIN(K13,Assumptions!$B$9),0)) | Q13: =IF($B13="","",IF(G13<=Assumptions!$B$10,ROUNDUP(N13*Assumptions!$B$11,0),0)) | R13: =IF($B13="","",TDS_Working!K13) | S13: =IF($B13="","",P13+Q13+R13) | T13: =IF($B13="","",N13-S13) | U13: =IF($B13="","",ROUND(Assumptions!$B$8*MIN(K13,Assumptions!$B$9),0)) | V13: =IF($B13="","",IF(G13<=Assumptions!$B$10,ROUNDUP(N13*Assumptions!$B$12,0),0)) | W13: =IF($B13="","",N13+U13+V13)
A14: 10 | E14: =IF($B14="","",ROUND(D14*Assumptions!$B$6,0)) | G14: =IF($B14="","",D14+E14+F14) | H14: =IF($B14="","",Assumptions!$B$5) | J14: =IF($B14="","",H14-I14) | K14: =IF($B14="","",ROUND(D14*J14/H14,0)) | L14: =IF($B14="","",ROUND(E14*J14/H14,0)) | M14: =IF($B14="","",ROUND(F14*J14/H14,0)) | N14: =IF($B14="","",K14+L14+M14) | O14: =IF($B14="","",G14-N14) | P14: =IF($B14="","",ROUND(Assumptions!$B$7*MIN(K14,Assumptions!$B$9),0)) | Q14: =IF($B14="","",IF(G14<=Assumptions!$B$10,ROUNDUP(N14*Assumptions!$B$11,0),0)) | R14: =IF($B14="","",TDS_Working!K14) | S14: =IF($B14="","",P14+Q14+R14) | T14: =IF($B14="","",N14-S14) | U14: =IF($B14="","",ROUND(Assumptions!$B$8*MIN(K14,Assumptions!$B$9),0)) | V14: =IF($B14="","",IF(G14<=Assumptions!$B$10,ROUNDUP(N14*Assumptions!$B$12,0),0)) | W14: =IF($B14="","",N14+U14+V14)
A15: 11 | E15: =IF($B15="","",ROUND(D15*Assumptions!$B$6,0)) | G15: =IF($B15="","",D15+E15+F15) | H15: =IF($B15="","",Assumptions!$B$5) | J15: =IF($B15="","",H15-I15) | K15: =IF($B15="","",ROUND(D15*J15/H15,0)) | L15: =IF($B15="","",ROUND(E15*J15/H15,0)) | M15: =IF($B15="","",ROUND(F15*J15/H15,0)) | N15: =IF($B15="","",K15+L15+M15) | O15: =IF($B15="","",G15-N15) | P15: =IF($B15="","",ROUND(Assumptions!$B$7*MIN(K15,Assumptions!$B$9),0)) | Q15: =IF($B15="","",IF(G15<=Assumptions!$B$10,ROUNDUP(N15*Assumptions!$B$11,0),0)) | R15: =IF($B15="","",TDS_Working!K15) | S15: =IF($B15="","",P15+Q15+R15) | T15: =IF($B15="","",N15-S15) | U15: =IF($B15="","",ROUND(Assumptions!$B$8*MIN(K15,Assumptions!$B$9),0)) | V15: =IF($B15="","",IF(G15<=Assumptions!$B$10,ROUNDUP(N15*Assumptions!$B$12,0),0)) | W15: =IF($B15="","",N15+U15+V15)
A16: 12 | E16: =IF($B16="","",ROUND(D16*Assumptions!$B$6,0)) | G16: =IF($B16="","",D16+E16+F16) | H16: =IF($B16="","",Assumptions!$B$5) | J16: =IF($B16="","",H16-I16) | K16: =IF($B16="","",ROUND(D16*J16/H16,0)) | L16: =IF($B16="","",ROUND(E16*J16/H16,0)) | M16: =IF($B16="","",ROUND(F16*J16/H16,0)) | N16: =IF($B16="","",K16+L16+M16) | O16: =IF($B16="","",G16-N16) | P16: =IF($B16="","",ROUND(Assumptions!$B$7*MIN(K16,Assumptions!$B$9),0)) | Q16: =IF($B16="","",IF(G16<=Assumptions!$B$10,ROUNDUP(N16*Assumptions!$B$11,0),0)) | R16: =IF($B16="","",TDS_Working!K16) | S16: =IF($B16="","",P16+Q16+R16) | T16: =IF($B16="","",N16-S16) | U16: =IF($B16="","",ROUND(Assumptions!$B$8*MIN(K16,Assumptions!$B$9),0)) | V16: =IF($B16="","",IF(G16<=Assumptions!$B$10,ROUNDUP(N16*Assumptions!$B$12,0),0)) | W16: =IF($B16="","",N16+U16+V16)
B17: TOTAL | D17: =SUM(D5:D16) -> 219000 | E17: =SUM(E5:E16) -> 87600 | F17: =SUM(F5:F16) -> 132900 | G17: =SUM(G5:G16) -> 439500 | K17: =SUM(K5:K16) -> 215733 | L17: =SUM(L5:L16) -> 86293 | M17: =SUM(M5:M16) -> 131440 | N17: =SUM(N5:N16) -> 433466 | O17: =SUM(O5:O16) -> 6034 | P17: =SUM(P5:P16) -> 12840 | Q17: =SUM(Q5:Q16) -> 217 | R17: =SUM(R5:R16) -> 17091 | ... W17: =SUM(W5:W16) -> 447243
A19: Notes: HRA defaults to the % in Assumptions. PF = 12% of earned Basic up to the Rs 15,000 ceiling. ESI applies when fixed gross is up to Rs 21,000. TDS is linked from TDS_Working. Net Salary = Earned Gross - PF - ESI - TDS.
A20: Rows 5-16 hold up to 12 employees. To add one, type name, designation, Basic, Special Allowance and LOP days in the next blank row; add the same name order in TDS_Working (it reads Payroll_Master automatically).

Sheet TDS_Working
A1: TDS on Salary - Section 392 (erstwhile 192) Working
A2: New tax regime FY 2026-27. Annual projection on fixed gross; monthly TDS = annual tax / 12.
A4: Sr | B4: Employee | C4: Monthly Gross (Fixed) | D4: Annual Gross | E4: Standard Deduction | F4: Taxable Income | G4: Tax as per Slabs | H4: Tax after Rebate / Marginal Relief | I4: Cess | J4: Annual Tax | K4: Monthly TDS
A5: 1 | B5: =IF(Payroll_Master!$B5="","",Payroll_Master!B5) -> Rakesh Sahoo | C5: =IF(Payroll_Master!$B5="","",Payroll_Master!G5) -> 153000 | D5: =IF(Payroll_Master!$B5="","",C5*Assumptions!$B$16) -> 1836000 | E5: =IF(Payroll_Master!$B5="","",Assumptions!$B$13) -> 75000 | F5: =IF(Payroll_Master!$B5="","",MAX(0,D5-E5)) -> 1761000 | G5: =IF(Payroll_Master!$B5="","",ROUND(SUMPRODUCT((F5>Assumptions!$A$20:$A$25)*(F5-Assumptions!$A$20:$A$25)*Assumptions!$D$20:$D$25),0)) -> 152200 | H5: =IF(Payroll_Master!$B5="","",IF(F5<=Assumptions!$B$14,0,MIN(G5,F5-Assumptions!$B$14))) -> 152200 | I5: =IF(Payroll_Master!$B5="","",ROUND(H5*Assumptions!$B$15,0)) -> 6088 | J5: =IF(Payroll_Master!$B5="","",H5+I5) -> 158288 | K5: =IF(Payroll_Master!$B5="","",ROUND(J5/Assumptions!$B$16,0)) -> 13191
A6: 2 | B6: =IF(Payroll_Master!$B6="","",Payroll_Master!B6) -> Smita Mohanty | C6: =IF(Payroll_Master!$B6="","",Payroll_Master!G6) -> 110000 | D6: =IF(Payroll_Master!$B6="","",C6*Assumptions!$B$16) -> 1320000 | E6: =IF(Payroll_Master!$B6="","",Assumptions!$B$13) -> 75000 | F6: =IF(Payroll_Master!$B6="","",MAX(0,D6-E6)) -> 1245000 | G6: =IF(Payroll_Master!$B6="","",ROUND(SUMPRODUCT((F6>Assumptions!$A$20:$A$25)*(F6-Assumptions!$A$20:$A$25)*Assumptions!$D$20:$D$25),0)) -> 66750 | H6: =IF(Payroll_Master!$B6="","",IF(F6<=Assumptions!$B$14,0,MIN(G6,F6-Assumptions!$B$14))) -> 45000 | I6: =IF(Payroll_Master!$B6="","",ROUND(H6*Assumptions!$B$15,0)) -> 1800 | J6: =IF(Payroll_Master!$B6="","",H6+I6) -> 46800 | K6: =IF(Payroll_Master!$B6="","",ROUND(J6/Assumptions!$B$16,0)) -> 3900
A7: 3 | B7: =IF(Payroll_Master!$B7="","",Payroll_Master!B7) -> Prakash Nayak | C7: =IF(Payroll_Master!$B7="","",Payroll_Master!G7) -> 50000 | D7: =IF(Payroll_Master!$B7="","",C7*Assumptions!$B$16) -> 600000 | E7: =IF(Payroll_Master!$B7="","",Assumptions!$B$13) -> 75000 | F7: =IF(Payroll_Master!$B7="","",MAX(0,D7-E7)) -> 525000 | G7: =IF(Payroll_Master!$B7="","",ROUND(SUMPRODUCT((F7>Assumptions!$A$20:$A$25)*(F7-Assumptions!$A$20:$A$25)*Assumptions!$D$20:$D$25),0)) -> 6250 | H7: =IF(Payroll_Master!$B7="","",IF(F7<=Assumptions!$B$14,0,MIN(G7,F7-Assumptions!$B$14))) -> 0 | I7: =IF(Payroll_Master!$B7="","",ROUND(H7*Assumptions!$B$15,0)) -> 0 | J7: =IF(Payroll_Master!$B7="","",H7+I7) -> 0 | K7: =IF(Payroll_Master!$B7="","",ROUND(J7/Assumptions!$B$16,0)) -> 0
A8: 4 | B8: =IF(Payroll_Master!$B8="","",Payroll_Master!B8) -> Anita Das | C8: =IF(Payroll_Master!$B8="","",Payroll_Master!G8) -> 40000 | D8: =IF(Payroll_Master!$B8="","",C8*Assumptions!$B$16) -> 480000 | E8: =IF(Payroll_Master!$B8="","",Assumptions!$B$13) -> 75000 | F8: =IF(Payroll_Master!$B8="","",MAX(0,D8-E8)) -> 405000 | G8: =IF(Payroll_Master!$B8="","",ROUND(SUMPRODUCT((F8>Assumptions!$A$20:$A$25)*(F8-Assumptions!$A$20:$A$25)*Assumptions!$D$20:$D$25),0)) -> 250 | H8: =IF(Payroll_Master!$B8="","",IF(F8<=Assumptions!$B$14,0,MIN(G8,F8-Assumptions!$B$14))) -> 0 | I8: =IF(Payroll_Master!$B8="","",ROUND(H8*Assumptions!$B$15,0)) -> 0 | J8: =IF(Payroll_Master!$B8="","",H8+I8) -> 0 | K8: =IF(Payroll_Master!$B8="","",ROUND(J8/Assumptions!$B$16,0)) -> 0
A9: 5 | B9: =IF(Payroll_Master!$B9="","",Payroll_Master!B9) -> Sanjay Behera | C9: =IF(Payroll_Master!$B9="","",Payroll_Master!G9) -> 30000 | D9: =IF(Payroll_Master!$B9="","",C9*Assumptions!$B$16) -> 360000 | E9: =IF(Payroll_Master!$B9="","",Assumptions!$B$13) -> 75000 | F9: =IF(Payroll_Master!$B9="","",MAX(0,D9-E9)) -> 285000 | G9: =IF(Payroll_Master!$B9="","",ROUND(SUMPRODUCT((F9>Assumptions!$A$20:$A$25)*(F9-Assumptions!$A$20:$A$25)*Assumptions!$D$20:$D$25),0)) -> 0 | H9: =IF(Payroll_Master!$B9="","",IF(F9<=Assumptions!$B$14,0,MIN(G9,F9-Assumptions!$B$14))) -> 0 | I9: =IF(Payroll_Master!$B9="","",ROUND(H9*Assumptions!$B$15,0)) -> 0 | J9: =IF(Payroll_Master!$B9="","",H9+I9) -> 0 | K9: =IF(Payroll_Master!$B9="","",ROUND(J9/Assumptions!$B$16,0)) -> 0
A10: 6 | B10: =IF(Payroll_Master!$B10="","",Payroll_Master!B10) -> Pooja Sharma | C10: =IF(Payroll_Master!$B10="","",Payroll_Master!G10) -> 26000 | D10: =IF(Payroll_Master!$B10="","",C10*Assumptions!$B$16) -> 312000 | E10: =IF(Payroll_Master!$B10="","",Assumptions!$B$13) -> 75000 | F10: =IF(Payroll_Master!$B10="","",MAX(0,D10-E10)) -> 237000 | G10: =IF(Payroll_Master!$B10="","",ROUND(SUMPRODUCT((F10>Assumptions!$A$20:$A$25)*(F10-Assumptions!$A$20:$A$25)*Assumptions!$D$20:$D$25),0)) -> 0 | H10: =IF(Payroll_Master!$B10="","",IF(F10<=Assumptions!$B$14,0,MIN(G10,F10-Assumptions!$B$14))) -> 0 | I10: =IF(Payroll_Master!$B10="","",ROUND(H10*Assumptions!$B$15,0)) -> 0 | J10: =IF(Payroll_Master!$B10="","",H10+I10) -> 0 | K10: =IF(Payroll_Master!$B10="","",ROUND(J10/Assumptions!$B$16,0)) -> 0
A11: 7 | B11: =IF(Payroll_Master!$B11="","",Payroll_Master!B11) -> Ramesh Pradhan | C11: =IF(Payroll_Master!$B11="","",Payroll_Master!G11) -> 17000 | D11: =IF(Payroll_Master!$B11="","",C11*Assumptions!$B$16) -> 204000 | E11: =IF(Payroll_Master!$B11="","",Assumptions!$B$13) -> 75000 | F11: =IF(Payroll_Master!$B11="","",MAX(0,D11-E11)) -> 129000 | G11: =IF(Payroll_Master!$B11="","",ROUND(SUMPRODUCT((F11>Assumptions!$A$20:$A$25)*(F11-Assumptions!$A$20:$A$25)*Assumptions!$D$20:$D$25),0)) -> 0 | H11: =IF(Payroll_Master!$B11="","",IF(F11<=Assumptions!$B$14,0,MIN(G11,F11-Assumptions!$B$14))) -> 0 | I11: =IF(Payroll_Master!$B11="","",ROUND(H11*Assumptions!$B$15,0)) -> 0 | J11: =IF(Payroll_Master!$B11="","",H11+I11) -> 0 | K11: =IF(Payroll_Master!$B11="","",ROUND(J11/Assumptions!$B$16,0)) -> 0
A12: 8 | B12: =IF(Payroll_Master!$B12="","",Payroll_Master!B12) -> Lata Munda | C12: =IF(Payroll_Master!$B12="","",Payroll_Master!G12) -> 13500 | D12: =IF(Payroll_Master!$B12="","",C12*Assumptions!$B$16) -> 162000 | E12: =IF(Payroll_Master!$B12="","",Assumptions!$B$13) -> 75000 | F12: =IF(Payroll_Master!$B12="","",MAX(0,D12-E12)) -> 87000 | G12: =IF(Payroll_Master!$B12="","",ROUND(SUMPRODUCT((F12>Assumptions!$A$20:$A$25)*(F12-Assumptions!$A$20:$A$25)*Assumptions!$D$20:$D$25),0)) -> 0 | H12: =IF(Payroll_Master!$B12="","",IF(F12<=Assumptions!$B$14,0,MIN(G12,F12-Assumptions!$B$14))) -> 0 | I12: =IF(Payroll_Master!$B12="","",ROUND(H12*Assumptions!$B$15,0)) -> 0 | J12: =IF(Payroll_Master!$B12="","",H12+I12) -> 0 | K12: =IF(Payroll_Master!$B12="","",ROUND(J12/Assumptions!$B$16,0)) -> 0
A13: 9 | B13: =IF(Payroll_Master!$B13="","",Payroll_Master!B13) | C13: =IF(Payroll_Master!$B13="","",Payroll_Master!G13) | D13: =IF(Payroll_Master!$B13="","",C13*Assumptions!$B$16) | E13: =IF(Payroll_Master!$B13="","",Assumptions!$B$13) | F13: =IF(Payroll_Master!$B13="","",MAX(0,D13-E13)) | G13: =IF(Payroll_Master!$B13="","",ROUND(SUMPRODUCT((F13>Assumptions!$A$20:$A$25)*(F13-Assumptions!$A$20:$A$25)*Assumptions!$D$20:$D$25),0)) | H13: =IF(Payroll_Master!$B13="","",IF(F13<=Assumptions!$B$14,0,MIN(G13,F13-Assumptions!$B$14))) | I13: =IF(Payroll_Master!$B13="","",ROUND(H13*Assumptions!$B$15,0)) | J13: =IF(Payroll_Master!$B13="","",H13+I13) | K13: =IF(Payroll_Master!$B13="","",ROUND(J13/Assumptions!$B$16,0))
A14: 10 | B14: =IF(Payroll_Master!$B14="","",Payroll_Master!B14) | C14: =IF(Payroll_Master!$B14="","",Payroll_Master!G14) | D14: =IF(Payroll_Master!$B14="","",C14*Assumptions!$B$16) | E14: =IF(Payroll_Master!$B14="","",Assumptions!$B$13) | F14: =IF(Payroll_Master!$B14="","",MAX(0,D14-E14)) | G14: =IF(Payroll_Master!$B14="","",ROUND(SUMPRODUCT((F14>Assumptions!$A$20:$A$25)*(F14-Assumptions!$A$20:$A$25)*Assumptions!$D$20:$D$25),0)) | H14: =IF(Payroll_Master!$B14="","",IF(F14<=Assumptions!$B$14,0,MIN(G14,F14-Assumptions!$B$14))) | I14: =IF(Payroll_Master!$B14="","",ROUND(H14*Assumptions!$B$15,0)) | J14: =IF(Payroll_Master!$B14="","",H14+I14) | K14: =IF(Payroll_Master!$B14="","",ROUND(J14/Assumptions!$B$16,0))
A15: 11 | B15: =IF(Payroll_Master!$B15="","",Payroll_Master!B15) | C15: =IF(Payroll_Master!$B15="","",Payroll_Master!G15) | D15: =IF(Payroll_Master!$B15="","",C15*Assumptions!$B$16) | E15: =IF(Payroll_Master!$B15="","",Assumptions!$B$13) | F15: =IF(Payroll_Master!$B15="","",MAX(0,D15-E15)) | G15: =IF(Payroll_Master!$B15="","",ROUND(SUMPRODUCT((F15>Assumptions!$A$20:$A$25)*(F15-Assumptions!$A$20:$A$25)*Assumptions!$D$20:$D$25),0)) | H15: =IF(Payroll_Master!$B15="","",IF(F15<=Assumptions!$B$14,0,MIN(G15,F15-Assumptions!$B$14))) | I15: =IF(Payroll_Master!$B15="","",ROUND(H15*Assumptions!$B$15,0)) | J15: =IF(Payroll_Master!$B15="","",H15+I15) | K15: =IF(Payroll_Master!$B15="","",ROUND(J15/Assumptions!$B$16,0))
A16: 12 | B16: =IF(Payroll_Master!$B16="","",Payroll_Master!B16) | C16: =IF(Payroll_Master!$B16="","",Payroll_Master!G16) | D16: =IF(Payroll_Master!$B16="","",C16*Assumptions!$B$16) | E16: =IF(Payroll_Master!$B16="","",Assumptions!$B$13) | F16: =IF(Payroll_Master!$B16="","",MAX(0,D16-E16)) | G16: =IF(Payroll_Master!$B16="","",ROUND(SUMPRODUCT((F16>Assumptions!$A$20:$A$25)*(F16-Assumptions!$A$20:$A$25)*Assumptions!$D$20:$D$25),0)) | H16: =IF(Payroll_Master!$B16="","",IF(F16<=Assumptions!$B$14,0,MIN(G16,F16-Assumptions!$B$14))) | I16: =IF(Payroll_Master!$B16="","",ROUND(H16*Assumptions!$B$15,0)) | J16: =IF(Payroll_Master!$B16="","",H16+I16) | K16: =IF(Payroll_Master!$B16="","",ROUND(J16/Assumptions!$B$16,0))
B17: TOTAL | C17: =SUM(C5:C16) -> 439500 | D17: =SUM(D5:D16) -> 5274000 | F17: =SUM(F5:F16) -> 4674000 | G17: =SUM(G5:G16) -> 225450 | H17: =SUM(H5:H16) -> 197200 | I17: =SUM(I5:I16) -> 7888 | J17: =SUM(J5:J16) -> 205088 | K17: =SUM(K5:K16) -> 17091
A19: Rebate: no tax if taxable income is up to the rebate limit. Just above it, tax is limited to the income above the limit (marginal relief). Employees with annual gross up to about Rs 12.75 lakh show nil TDS.
A20: Simplification: other income, deductions declared by the employee and previous-employer salary are ignored. Verify the slabs on Assumptions against the latest Finance Act.

Sheet Tally_Journal
A1: Payroll Journal Entry for Tally Prime - April 2026
A2: Figures link to Payroll_Master. Pass this in Tally (Vouchers > F7 Journal), then pass the payment vouchers when salary and dues are paid.
A4: 1. PAYROLL JOURNAL ENTRY | Voucher type: Journal | Date: 30-Apr-2026
A5: Ledger Account | B5: Group (create if not present) | C5: Debit (Rs) | D5: Credit (Rs)
A6: Salary Expense A/c | B6: Indirect Expenses | C6: =Payroll_Master!W17 -> 447243
A7: Salary Payable A/c | B7: Current Liabilities | D7: =Payroll_Master!T17 -> 403318
A8: PF Payable A/c (employee + employer) | B8: Current Liabilities | D8: =Payroll_Master!P17+Payroll_Master!U17 -> 25680
A9: ESI Payable A/c (employee + employer) | B9: Current Liabilities | D9: =Payroll_Master!Q17+Payroll_Master!V17 -> 1154
A10: TDS Payable A/c (salary TDS) | B10: Duties & Taxes (already exists) | D10: =Payroll_Master!R17 -> 17091
A11: TOTAL | C11: =SUM(C6:C10) -> 447243 | D11: =SUM(D6:D10) -> 447243
A12: Check: Debit - Credit (must be 0) | C12: =C11-D11 -> 0
A13: Narration: Being salary of April 2026 booked, with employee and employer PF/ESI and TDS on salary (Sec 392, erstwhile 192) payable.
A15: 2. PAYMENT VOUCHERS (pass when paid)
A16: Payment | B16: Voucher / Entries | C16: Amount (Rs) | D16: Due date
A17: Salary paid to employees | B17: Payment: Dr Salary Payable A/c, Cr HDFC Bank A/c | C17: =Payroll_Master!T17 -> 403318 | D17: 46142
A18: TDS on salary deposited | B18: Payment: Dr TDS Payable A/c, Cr HDFC Bank A/c | C18: =Payroll_Master!R17 -> 17091 | D18: 46149
A19: PF deposited | B19: Payment: Dr PF Payable A/c, Cr HDFC Bank A/c | C19: =Payroll_Master!P17+Payroll_Master!U17 -> 25680 | D19: 46157
A20: ESI deposited | B20: Payment: Dr ESI Payable A/c, Cr HDFC Bank A/c | C20: =Payroll_Master!Q17+Payroll_Master!V17 -> 1154 | D20: 46157
A21: Due dates: TDS by 7th and PF/ESI by 15th of the following month (statutory dates). Salary payment date is assumed 30-Apr-26. Payment vouchers reduce the bank balance, so enter them in Tally and in the Bank statement only when you want them in the books.
A23: 3. STEPS IN TALLY PRIME
A24: 1. Gateway of Tally > Create > Ledger. Create Salary Expense A/c (Under: Indirect Expenses).
A25: 2. Create Salary Payable A/c, PF Payable A/c and ESI Payable A/c (Under: Current Liabilities). TDS Payable A/c already exists.
A26: 3. Gateway of Tally > Vouchers > press F7 (Journal). Set the date to 30-Apr-2026.
A27: 4. Dr Salary Expense A/c with the debit amount above. Then Cr Salary Payable, PF Payable, ESI Payable and TDS Payable with the credit amounts above.
A28: 5. Add the narration and press Ctrl+A to save. Total Dr must equal total Cr.
A29: 6. Check Display More Reports > Trial Balance. Salary Expense now appears under Indirect Expenses and the new payables under Current Liabilities.
A30: 7. Pass the payment vouchers (F5 Payment) from section 2 when the salary and dues are paid.
A32: After posting, the P&L loss will increase because salary expense is added. This is expected for the practice data; increase the Sales figure if you want the project to show a profit.

Sheet Assumptions
A1: Payroll Assumptions and Rates
A2: Blue / yellow cells are inputs. All payroll and TDS sheets read from here. Dummy data for practice.
A3: Parameter | B3: Value | C3: Note
A4: Pay period | B4: April 2026 | C4: Month-end payroll for Nexus Tech Distribution Pvt. Ltd.
A5: Days in month | B5: 30 | C5: Calendar days used for LOP (loss of pay) calculation
A6: HRA as % of Basic | B6: 0.4 | C6: Assumed 40% (non-metro). Used only to fill HRA by default
A7: PF - employee rate | B7: 0.12 | C7: On Basic, subject to wage ceiling below
A8: PF - employer rate | B8: 0.12 | C8: Assumed at 12% for this practice project; actual EPF/EPS and administrative charges may be accounted for separately
A9: PF wage ceiling (Rs) | B9: 15000 | C9: PF calculated on Basic up to this amount (assumption)
A10: ESI applies if monthly gross up to (Rs) | B10: 21000 | C10: Eligibility based on fixed monthly gross
A11: ESI - employee rate | B11: 0.0075 | C11: 0.75% of earned gross
A12: ESI - employer rate | B12: 0.0325 | C12: 3.25% of earned gross
A13: Standard deduction (Rs) | B13: 75000 | C13: New tax regime, salaried employees
A14: Rebate limit - taxable income (Rs) | B14: 1200000 | C14: No tax up to this taxable income (with marginal relief just above it)
A15: Health & education cess | B15: 0.04 | C15: On income tax
A16: Months in year | B16: 12 | C16: Monthly TDS = annual tax / 12
A18: New tax regime slabs (default regime)
A19: Slab starts above (Rs) | B19: Slab ends at (Rs) | C19: Rate on slab | D19: Incremental rate (used in formula)
A20: 400000 | B20: 800000 | C20: 0.05 | D20: =C20 -> 0.05
A21: 800000 | B21: 1200000 | C21: 0.1 | D21: =C21-C20 -> 0.05
A22: 1200000 | B22: 1600000 | C22: 0.15 | D22: =C22-C21 -> 0.05
A23: 1600000 | B23: 2000000 | C23: 0.2 | D23: =C23-C22 -> 0.05
A24: 2000000 | B24: 2400000 | C24: 0.25 | D24: =C24-C23 -> 0.05
A25: 2400000 | B25: and above | C25: 0.3 | D25: =C25-C24 -> 0.05
A26: Income up to Rs 4,00,000 is nil. Tax = sum over slabs of (income above slab start) x incremental rate.
A28: Legal note
A29: 1. From 1-Apr-2026 the Income-tax Act, 2025 applies. TDS on salary is under Section 392 (erstwhile Section 192 of the 1961 Act). Rates and slabs shown are the new-regime slabs for FY 2026-27 as per published guides; please verify against the latest Finance Act before real use.
A30: 2. TDS is a projection: annual tax on fixed gross less standard deduction, divided by 12. Other income, declarations and previous-employer salary are ignored (simplification).
A31: 3. ESI contribution is rounded up to the next rupee. Professional Tax is not included.
